{"type":"FeatureCollection","features":[{"type":"Feature","properties":{"OBJECTID":"12","Facility_N":"AAR Health Care-Kisumu","Type":"Medical Clinic","Owner":"Private Practice - General Practitioner","County":"Kisumu","Sub_County":"Kisumu East","Division":"Winam","Location":"Township","Sub_Locati":"Market Milimani","Constituen":"KISUMU TOWN EAST","Nearest_To":"Central Business District","Latitude":"-0.10465","Longitude":"34.75328"},"geometry":{"type":"Point","coordinates":[34.75328,-0.10465]}},{"type":"Feature","properties":{"OBJECTID":"38","Facility_N":"Absalom Wangulu Dispensary","Type":"Dispensary","Owner":"Ministry of Health","County":"Kisumu","Sub_County":"Nyando","Division":"Kadibo","Location":"Kombura","Sub_Locati":"Masogo","Constituen":"NYANDO","Nearest_To":"Rabuor","Latitude":"-0.17013","Longitude":"34.84837"},"geometry":{"type":"Point","coordinates":[34.84837,-0.17013]}},{"type":"Feature","properties":{"OBJECTID":"39","Facility_N":"Abundant Life Clinic","Type":"Medical Clinic","Owner":"Private Enterprise (Institution)","County":"Kisumu","Sub_County":"Kisumu East","Division":"Winam","Location":"Nyalenda","Sub_Locati":"Nyalenda A","Constituen":"KISUMU TOWN EAST","Nearest_To":"Kisumu Town","Latitude":"-0.122486","Longitude":"34.752132"},"geometry":{"type":"Point","coordinates":[34.752132,-0.122486]}},{"type":"Feature","properties":{"OBJECTID":"60","Facility_N":"Administration Police Dispensary (Kisumu East)","Type":"Dispensary","Owner":"Ministry of Health","County":"Kisumu","Sub_County":"Kisumu East","Division":"Winam","Location":"Township","Sub_Locati":"Southern","Constituen":"KISUMU TOWN EAST","Nearest_To":"Kisumu","Latitude":"-0.12409","Longitude":"34.75813"},"geometry":{"type":"Point","coordinates":[34.75813,-0.12409]}},{"type":"Feature","properties":{"OBJECTID":"134","Facility_N":"Aga Khan Hospital (Kisumu)","Type":"Other Hospital","Owner":"Private Enterprise (Institution)","County":"Kisumu","Sub_County":"Kisumu East","Division":"Winam","Location":"Township","Sub_Locati":"Southern","Constituen":"KISUMU TOWN EAST","Nearest_To":"Kisumu","Latitude":"-0.09937","Longitude":"34.75621"},"geometry":{"type":"Point","coordinates":[34.75621,-0.09937]}},{"type":"Feature","properties":{"OBJECTID":"155","Facility_N":"Agro Chemical Dispensary","Type":"Dispensary","Owner":"Private Enterprise (Institution)","County":"Kisumu","Sub_County":"Muhoroni","Division":"Muhoroni","Location":"God Nyithindo","Sub_Locati":"Orego","Constituen":"MUHORONI","Nearest_To":"Muhoroni Township Market","Latitude":"0.0","Longitude":"35.0"},"geometry":{"type":"Point","coordinates":[35,0]}},{"type":"Feature","properties":{"OBJECTID":"159","Facility_N":"Ahero County Hospital","Type":"Other Hospital","Owner":"Ministry of Health","County":"Kisumu","Sub_County":"Nyando","Division":"Nyando","Location":"Kakola","Sub_Locati":"Kakola Ahero","Constituen":"NYANDO","Nearest_To":"Ahero","Latitude":"-0.17321","Longitude":"34.92367"},"geometry":{"type":"Point","coordinates":[34.92367,-0.17321]}},{"type":"Feature","properties":{"OBJECTID":"160","Facility_N":"Ahero Medical Centre","Type":"Medical Clinic","Owner":"Private Practice - Nurse / Midwife","County":"Kisumu","Sub_County":"Nyando","Division":"Nyando","Location":"Onjiko","Sub_Locati":"Kakmie","Constituen":"NYANDO","Nearest_To":"Ahero","Latitude":"-0.17296","Longitude":"34.92412"},"geometry":{"type":"Point","coordinates":[34.92412,-0.17296]}},{"type":"Feature","properties":{"OBJECTID":"185","Facility_N":"Airport Dispensary (Kisumu)","Type":"Dispensary","Owner":"Local Authority","County":"Kisumu","Sub_County":"Kisumu West","Division":"Winam","Location":"East Kisumu","Sub_Locati":"Kogony","Constituen":"KISUMU TOWN EAST","Nearest_To":"Kisumu","Latitude":"-0.07331","Longitude":"34.73359"},"geometry":{"type":"Point","coordinates":[34.73359,-0.07331]}},{"type":"Feature","properties":{"OBJECTID":"215","Facility_N":"AL Nur Medical Clinic & Laboratory","Type":"Medical Clinic","Owner":"Private Enterprise (Institution)","County":"Kisumu","Sub_County":"Kisumu East","Division":"Winam","Location":"Township","Sub_Locati":"Southern","Constituen":"KISUMU TOWN EAST","Nearest_To":"Stage Market","Latitude":"-0.10131","Longitude":"34.76148"},"geometry":{"type":"Point","coordinates":[34.76148,-0.10131]}},{"type":"Feature","properties":{"OBJECTID":"329","Facility_N":"Anding'o Opanga Dispensary","Type":"Dispensary","Owner":"Ministry of Health","County":"Kisumu","Sub_County":"Nyakach","Division":"Upper Nyakach","Location":"Thurdibuoro","Sub_Locati":"Anding' Opanga","Constituen":"NYAKACH","Nearest_To":"Anding' Opanga","Latitude":"-0.3624","Longitude":"34.8405"},"geometry":{"type":"Point","coordinates":[34.8405,-0.3624]}},{"type":"Feature","properties":{"OBJECTID":"339","Facility_N":"Angola Community Dispensary","Type":"Dispensary","Owner":"Ministry of Health","County":"Kisumu","Sub_County":"Kisumu East","Division":"Winam","Location":"Kolwa East","Sub_Locati":"Mayenya","Constituen":"KISUMU TOWN EAST","Nearest_To":"Angola Market","Latitude":"-0.12713","Longitude":"34.8245"},"geometry":{"type":"Point","coordinates":[34.8245,-0.12713]}},{"type":"Feature","properties":{"OBJECTID":"364","Facility_N":"Anza Mapema-Drop in Dice","Type":"Medical Clinic","Owner":"Non-Governmental Organizations","County":"Kisumu","Sub_County":"Kisumu East","Division":"Winam","Location":"Township","Sub_Locati":"Township","Constituen":"KISUMU TOWN EAST","Nearest_To":"Tom Mboya Estate","Latitude":"-0.04721","Longitude":"34.67107"},"geometry":{"type":"Point","coordinates":[34.67107,-0.04721]}},{"type":"Feature","properties":{"OBJECTID":"399","Facility_N":"Arito Langi Dispensary","Type":"Dispensary","Owner":"Ministry of Health","County":"Kisumu","Sub_County":"Seme","Division":"Kombewa","Location":"West Seme","Sub_Locati":"West Reru","Constituen":"KISUMU RURAL","Nearest_To":"Kolenyo","Latitude":"-0.09448","Longitude":"34.44948"},"geometry":{"type":"Point","coordinates":[34.44948,-0.09448]}},{"type":"Feature","properties":{"OBJECTID":"412","Facility_N":"Asat Beach Dispensary","Type":"Dispensary","Owner":"Ministry of Health","County":"Kisumu","Sub_County":"Seme","Division":"Kombewa","Location":"South Central Seme","Sub_Locati":"West Othany","Constituen":"KISUMU RURAL","Nearest_To":"Asat Beach","Latitude":"-0.18267","Longitude":"34.51846"},"geometry":{"type":"Point","coordinates":[34.51846,-0.18267]}},{"type":"Feature","properties":{"OBJECTID":"447","Facility_N":"Avenue Health Care Clinic","Type":"Medical Clinic","Owner":"Private Enterprise (Institution)","County":"Kisumu","Sub_County":"Kisumu East","Division":"Winam","Location":"Township","Sub_Locati":"Southern","Constituen":"KISUMU TOWN EAST","Nearest_To":"Kisumu","Latitude":"-0.10463","Longitude":"34.75323"},"geometry":{"type":"Point","coordinates":[34.75323,-0.10463]}},{"type":"Feature","properties":{"OBJECTID":"452","Facility_N":"Avenue Hospital Kisumu","Type":"Other Hospital","Owner":"Private Enterprise (Institution)","County":"Kisumu","Sub_County":"Kisumu East","Division":"Winam","Location":"Manyatta B","Sub_Locati":" ","Constituen":"KISUMU TOWN EAST","Nearest_To":"Kibuye Market-Kisumu Kakamega Road","Latitude":"-0.088626","Longitude":"34.770387"},"geometry":{"type":"Point","coordinates":[34.770387,-0.088626]}},{"type":"Feature","properties":{"OBJECTID":"453","Facility_N":"Awasi Mission Health Center","Type":"Health Centre","Owner":"Kenya Episcopal Conference-Catholic Secretariat","County":"Kisumu","Sub_County":"Nyando","Division":"Nyando","Location":"Awasi","Sub_Locati":"Border I","Constituen":"NYANDO","Nearest_To":"Awasi","Latitude":"-0.16043","Longitude":"35.07395"},"geometry":{"type":"Point","coordinates":[35.07395,-0.16043]}},{"type":"Feature","properties":{"OBJECTID":"525","Facility_N":"Bar Korwa Dispensary","Type":"Dispensary","Owner":"Kenya Episcopal Conference-Catholic Secretariat","County":"Kisumu","Sub_County":"Seme","Division":"Kombewa","Location":"North Central Seme","Sub_Locati":"East Katieno","Constituen":"KISUMU RURAL","Nearest_To":"Bar Korwa","Latitude":"-0.06878","Longitude":"34.51293"},"geometry":{"type":"Point","coordinates":[34.51293,-0.06878]}},{"type":"Feature","properties":{"OBJECTID":"694","Facility_N":"Bodi Health Centre","Type":"Health Centre","Owner":"Ministry of Health","County":"Kisumu","Sub_County":"Seme","Division":"Kombewa","Location":"South Central Seme","Sub_Locati":"West Othany","Constituen":"KISUMU RURAL","Nearest_To":"Bodi Market","Latitude":"-0.16328","Longitude":"34.51242"},"geometry":{"type":"Point","coordinates":[34.51242,-0.16328]}},{"type":"Feature","properties":{"OBJECTID":"722","Facility_N":"Bonde Dispensary","Type":"Dispensary","Owner":"Ministry of Health","County":"Kisumu","Sub_County":"Nyakach","Division":"Lower Nyakach","Location":"Nyalunya","Sub_Locati":"Kabodho North","Constituen":"NYAKACH","Nearest_To":"Harambee","Latitude":"-0.31432","Longitude":"34.88627"},"geometry":{"type":"Point","coordinates":[34.88627,-0.31432]}},{"type":"Feature","properties":{"OBJECTID":"755","Facility_N":"Boya Nursing Home","Type":"Nursing Home","Owner":"Private Enterprise (Institution)","County":"Kisumu","Sub_County":"Nyando","Division":"Nyando","Location":"Kakola","Sub_Locati":"Kobong'o","Constituen":"NYANDO","Nearest_To":"Ahero","Latitude":"-0.16599","Longitude":"34.94904"},"geometry":{"type":"Point","coordinates":[34.94904,-0.16599]}},{"type":"Feature","properties":{"OBJECTID":"806","Facility_N":"Bunde Dispensary","Type":"Dispensary","Owner":"Ministry of Health","County":"Kisumu","Sub_County":"Nyando","Division":"Nyando","Location":"Kochogo","Sub_Locati":"Kochogo South","Constituen":"NYANDO","Nearest_To":"Ahero","Latitude":"-0.21854","Longitude":"34.89962"},"geometry":{"type":"Point","coordinates":[34.89962,-0.21854]}},{"type":"Feature","properties":{"OBJECTID":"889","Facility_N":"Careplus Medical Services","Type":"Medical Clinic","Owner":"Private Practice - General Practitioner","County":"Kisumu","Sub_County":"Kisumu East","Division":"Winam","Location":"Konya","Sub_Locati":" ","Constituen":"KISUMU TOWN EAST","Nearest_To":"Mamboleo","Latitude":"-0.058387","Longitude":"34.785175"},"geometry":{"type":"Point","coordinates":[34.785175,-0.058387]}},{"type":"Feature","properties":{"OBJECTID":"916","Facility_N":"Central Clinic (Kisumu East)","Type":"Medical Clinic","Owner":"Private Enterprise (Institution)","County":"Kisumu","Sub_County":"Kisumu East","Division":"Winam","Location":"Township","Sub_Locati":"Southern","Constituen":"KISUMU TOWN EAST","Nearest_To":"Kisumu","Latitude":"-0.127499","Longitude":"34.7252"},"geometry":{"type":"Point","coordinates":[34.7252,-0.127499]}},{"type":"Feature","properties":{"OBJECTID":"1016","Facility_N":"Chemelil GOK Dispensary","Type":"Dispensary","Owner":"Ministry of Health","County":"Kisumu","Sub_County":"Muhoroni","Division":"Miwani","Location":"Chemelil","Sub_Locati":"Chemelil","Constituen":"MUHORONI","Nearest_To":"Chemelil","Latitude":"-0.10732","Longitude":"35.10848"},"geometry":{"type":"Point","coordinates":[35.10848,-0.10732]}},{"type":"Feature","properties":{"OBJECTID":"1017","Facility_N":"Chemelil Sugar Health Centre","Type":"Health Centre","Owner":"Company Medical Service","County":"Kisumu","Sub_County":"Muhoroni","Division":"Muhoroni","Location":"Muhoroni","Sub_Locati":"Chemelil","Constituen":"MUHORONI","Nearest_To":"Chemelil","Latitude":"-0.15153","Longitude":"35.18239"},"geometry":{"type":"Point","coordinates":[35.18239,-0.15153]}},{"type":"Feature","properties":{"OBJECTID":"1127","Facility_N":"Cherwa Dispensary","Type":"Dispensary","Owner":"Ministry of Health","County":"Kisumu","Sub_County":"Nyakach","Division":"Lower Nyakach","Location":"North East Nyakach","Sub_Locati":"Agoro East","Constituen":"NYAKACH","Nearest_To":"Omuonyo le market","Latitude":"-0.29018","Longitude":"35.02825"},"geometry":{"type":"Point","coordinates":[35.02825,-0.29018]}},{"type":"Feature","properties":{"OBJECTID":"1153","Facility_N":"Chiga Dispensary","Type":"Dispensary","Owner":"Ministry of Health","County":"Kisumu","Sub_County":"Kisumu East","Division":"Winam","Location":"East Kolwa","Sub_Locati":"Chiga","Constituen":"KISUMU TOWN EAST","Nearest_To":"Kisumu","Latitude":"-0.09345","Longitude":"34.83829"},"geometry":{"type":"Point","coordinates":[34.83829,-0.09345]}},{"type":"Feature","properties":{"OBJECTID":"1187","Facility_N":"Chulaimbo Sub-District Hospital","Type":"Sub-District Hospital","Owner":"Ministry of Health","County":"Kisumu","Sub_County":"Kisumu West","Division":"Maseno","Location":"North West Kisumu","Sub_Locati":"Marera","Constituen":"KISUMU RURAL","Nearest_To":"Chulaimbo Market","Latitude":"-0.03785","Longitude":"34.63821"},"geometry":{"type":"Point","coordinates":[34.63821,-0.03785]}},{"type":"Feature","properties":{"OBJECTID":"1304","Facility_N":"Dago Jonyo Dispensary","Type":"Dispensary","Owner":"Ministry of Health","County":"Kisumu","Sub_County":"Seme","Division":"Kombewa","Location":"South West Seme","Sub_Locati":"South Alungo","Constituen":"KISUMU RURAL","Nearest_To":"Bodi Market","Latitude":"-0.18251","Longitude":"34.50411"},"geometry":{"type":"Point","coordinates":[34.50411,-0.18251]}},{"type":"Feature","properties":{"OBJECTID":"1394","Facility_N":"Disciples of Mercy Clinic","Type":"Medical Clinic","Owner":"Kenya Episcopal Conference-Catholic Secretariat","County":"Kisumu","Sub_County":"Kisumu East","Division":"Winam","Location":"Kajulu East","Sub_Locati":"Konya","Constituen":"KISUMU TOWN EAST","Nearest_To":"Kisumu","Latitude":"-0.05596","Longitude":"34.80129"},"geometry":{"type":"Point","coordinates":[34.80129,-0.05596]}},{"type":"Feature","properties":{"OBJECTID":"1604","Facility_N":"Dunga Nursing Home","Type":"Other Hospital","Owner":"Private Enterprise (Institution)","County":"Kisumu","Sub_County":"Kisumu East","Division":"Winam","Location":"Township","Sub_Locati":"Nyalenda B","Constituen":"KISUMU TOWN WEST","Nearest_To":"Kisumu","Latitude":"-0.13157","Longitude":"34.74435"},"geometry":{"type":"Point","coordinates":[34.74435,-0.13157]}},{"type":"Feature","properties":{"OBJECTID":"1937","Facility_N":"Family Health Options Kenya (FHOPK) Dispensary","Type":"Dispensary","Owner":"Non-Governmental Organizations","County":"Kisumu","Sub_County":"Kisumu East","Division":"Winam","Location":"West Kolwa","Sub_Locati":"Nyalenda A","Constituen":"KISUMU TOWN EAST","Nearest_To":"Kisumu","Latitude":"-0.10086","Longitude":"34.76096"},"geometry":{"type":"Point","coordinates":[34.76096,-0.10086]}},{"type":"Feature","properties":{"OBJECTID":"2066","Facility_N":"Gari Dispensary","Type":"Dispensary","Owner":"Ministry of Health","County":"Kisumu","Sub_County":"Nyakach","Division":"Upper Division","Location":"Oboch","Sub_Locati":"Gari","Constituen":"NYAKACH","Nearest_To":"Nyamarimba","Latitude":"-0.38029","Longitude":"34.91391"},"geometry":{"type":"Point","coordinates":[34.91391,-0.38029]}},{"type":"Feature","properties":{"OBJECTID":"2190","Facility_N":"Geva Family Health Services","Type":"Medical Clinic","Owner":"Private Practice - Clinical Officer","County":"Kisumu","Sub_County":"Kisumu East","Division":"Winam","Location":"Kolwa","Sub_Locati":"Kasule","Constituen":"KISUMU TOWN EAST","Nearest_To":"Nyamasaria Market","Latitude":"-0.116364","Longitude":"34.786922"},"geometry":{"type":"Point","coordinates":[34.786922,-0.116364]}},{"type":"Feature","properties":{"OBJECTID":"2233","Facility_N":"Gita Sub County Hospital","Type":"Sub-District Hospital","Owner":"Local Authority","County":"Kisumu","Sub_County":"Kisumu East","Division":"Winam","Location":"East Kajulu","Sub_Locati":"Kadero","Constituen":"KISUMU TOWN EAST","Nearest_To":"Kisumu","Latitude":"-0.02782","Longitude":"34.79048"},"geometry":{"type":"Point","coordinates":[34.79048,-0.02782]}},{"type":"Feature","properties":{"OBJECTID":"2325","Facility_N":"GK Prisons Dispensary (Kibos)","Type":"Dispensary","Owner":"Ministry of Health","County":"Kisumu","Sub_County":"Kisumu East","Division":"Winam","Location":"Miwani","Sub_Locati":"Central","Constituen":"KISUMU TOWN EAST","Nearest_To":"Kisumu","Latitude":"-0.06744","Longitude":"34.8209"},"geometry":{"type":"Point","coordinates":[34.8209,-0.06744]}},{"type":"Feature","properties":{"OBJECTID":"2335","Facility_N":"Global Providers International Clinic","Type":"Health Centre","Owner":"Non-Governmental Organizations","County":"Kisumu","Sub_County":"Kisumu East","Division":"Winam","Location":"Manyatta B","Sub_Locati":"Kondele","Constituen":"KISUMU TOWN EAST","Nearest_To":"Manyatta Market","Latitude":"-0.088293","Longitude":"34.779426"},"geometry":{"type":"Point","coordinates":[34.779426,-0.088293]}},{"type":"Feature","properties":{"OBJECTID":"2357","Facility_N":"Gods Will Clinic","Type":"Medical Clinic","Owner":"Private Enterprise (Institution)","County":"Kisumu","Sub_County":"Kisumu East","Division":"Winam","Location":"West Kolwa","Sub_Locati":"Nyalenda B","Constituen":"KISUMU TOWN EAST","Nearest_To":"Kisumu","Latitude":"-0.11741","Longitude":"34.75957"},"geometry":{"type":"Point","coordinates":[34.75957,-0.11741]}},{"type":"Feature","properties":{"OBJECTID":"2399","Facility_N":"Got Nyabondo Dispensary","Type":"Dispensary","Owner":"Local Authority","County":"Kisumu","Sub_County":"Kisumu East","Division":"Winam","Location":"East Kajulu","Sub_Locati":"Kadero","Constituen":"KISUMU TOWN EAST","Nearest_To":"Kisumu","Latitude":"-0.00573","Longitude":"34.80427"},"geometry":{"type":"Point","coordinates":[34.80427,-0.00573]}},{"type":"Feature","properties":{"OBJECTID":"2439","Facility_N":"Guru Nanak Dispensary","Type":"Dispensary","Owner":"Private Enterprise (Institution)","County":"Kisumu","Sub_County":"Kisumu East","Division":"Winam","Location":"Township","Sub_Locati":"Southern","Constituen":"KISUMU TOWN EAST","Nearest_To":"Kisumu","Latitude":"-0.10073","Longitude":"34.75253"},"geometry":{"type":"Point","coordinates":[34.75253,-0.10073]}},{"type":"Feature","properties":{"OBJECTID":"2501","Facility_N":"Helsamy Medical Clinic","Type":"Medical Clinic","Owner":"Private Practice - Clinical Officer","County":"Kisumu","Sub_County":"Kisumu East","Division":"Winam","Location":"Manyatta A","Sub_Locati":"Manyatta A","Constituen":"KISUMU TOWN EAST","Nearest_To":"Kondele -Manyatta Market","Latitude":"-0.085752","Longitude":"34.77809"},"geometry":{"type":"Point","coordinates":[34.77809,-0.085752]}},{"type":"Feature","properties":{"OBJECTID":"2547","Facility_N":"Holo Dispensary","Type":"Dispensary","Owner":"Ministry of Health","County":"Kisumu","Sub_County":"Nyando","Division":"Nyando","Location":"Awasi","Sub_Locati":"Border II","Constituen":"NYANDO","Nearest_To":"Awasi Market","Latitude":"-0.16982","Longitude":"35.10123"},"geometry":{"type":"Point","coordinates":[35.10123,-0.16982]}},{"type":"Feature","properties":{"OBJECTID":"2566","Facility_N":"Hongo Ogosa Health Centre","Type":"Health Centre","Owner":"Ministry of Health","County":"Kisumu","Sub_County":"Nyando","Division":"Kadibo","Location":"Katho","Sub_Locati":"Kamayoga","Constituen":"NYANDO","Nearest_To":"Ahero","Latitude":"-0.18603","Longitude":"34.89364"},"geometry":{"type":"Point","coordinates":[34.89364,-0.18603]}},{"type":"Feature","properties":{"OBJECTID":"2598","Facility_N":"House of Hope Medical Centre","Type":"Medical Clinic","Owner":"Private Practice - General Practitioner","County":"Kisumu","Sub_County":"Nyakach","Division":"Lower Nyakach","Location":"North East Nyakach","Sub_Locati":"Agoro West","Constituen":"NYAKACH","Nearest_To":"near Katito market","Latitude":"-0.26418","Longitude":"34.98087"},"geometry":{"type":"Point","coordinates":[34.98087,-0.26418]}},{"type":"Feature","properties":{"OBJECTID":"2778","Facility_N":"Impact Research-Tuungane (Nyando)","Type":"Medical Clinic","Owner":"Non-Governmental Organizations","County":"Kisumu","Sub_County":"Nyando","Division":"Nyando","Location":"Kakola Ahero","Sub_Locati":"Tura","Constituen":"NYANDO","Nearest_To":"Ahero","Latitude":"-0.17373","Longitude":"34.92714"},"geometry":{"type":"Point","coordinates":[34.92714,-0.17373]}},{"type":"Feature","properties":{"OBJECTID":"2793","Facility_N":"Interfelk Medical Centre","Type":"Medical Clinic","Owner":"Private Enterprise (Institution)","County":"Kisumu","Sub_County":"Kisumu East","Division":"Winam","Location":"West Kolwa","Sub_Locati":"Nyalenda A","Constituen":"KISUMU TOWN EAST","Nearest_To":"Kisumu","Latitude":"-0.11854","Longitude":"34.76114"},"geometry":{"type":"Point","coordinates":[34.76114,-0.11854]}},{"type":"Feature","properties":{"OBJECTID":"2895","Facility_N":"Jaber Dispensary","Type":"Dispensary","Owner":"Ministry of Health","County":"Kisumu","Sub_County":"Muhoroni","Division":"Muhoroni","Location":"God Nyithindo","Sub_Locati":"Tonde","Constituen":"MUHORONI","Nearest_To":"muhoroni market","Latitude":"0.13417","Longitude":"35.21683"},"geometry":{"type":"Point","coordinates":[35.21683,0.13417]}},{"type":"Feature","properties":{"OBJECTID":"2906","Facility_N":"Jalaram Nursing Home","Type":"Nursing Home","Owner":"Private Enterprise (Institution)","County":"Kisumu","Sub_County":"Kisumu East","Division":"Winam","Location":"Township","Sub_Locati":"Southern","Constituen":"KISUMU TOWN EAST","Nearest_To":"Kisumu","Latitude":"-0.09485","Longitude":"34.76432"},"geometry":{"type":"Point","coordinates":[34.76432,-0.09485]}},{"type":"Feature","properties":{"OBJECTID":"3054","Facility_N":"K- Met Clinic","Type":"Medical Clinic","Owner":"Non-Governmental Organizations","County":"Kisumu","Sub_County":"Kisumu East","Division":"Winam","Location":"Kolwa Central","Sub_Locati":"Kasule","Constituen":"KISUMU TOWN EAST","Nearest_To":"Kisumu","Latitude":"-0.1164","Longitude":"34.7871"},"geometry":{"type":"Point","coordinates":[34.7871,-0.1164]}},{"type":"Feature","properties":{"OBJECTID":"3139","Facility_N":"Kadinda Health Centre","Type":"Health Centre","Owner":"Non-Governmental Organizations","County":"Kisumu","Sub_County":"Nyando","Division":"Nyando","Location":"Kochogo","Sub_Locati":"Kochogo South","Constituen":"NYANDO","Nearest_To":"Ahero","Latitude":"-0.24004","Longitude":"34.89063"},"geometry":{"type":"Point","coordinates":[34.89063,-0.24004]}},{"type":"Feature","properties":{"OBJECTID":"3444","Facility_N":"Kandaria Medical Centre","Type":"Medical Clinic","Owner":"Private Practice - General Practitioner","County":"Kisumu","Sub_County":"Nyakach","Division":"Lower Nyakach","Location":"East Nyakach","Sub_Locati":"Kandaria","Constituen":"NYAKACH","Nearest_To":"Nduga","Latitude":"-0.33737","Longitude":"34.97995"},"geometry":{"type":"Point","coordinates":[34.97995,-0.33737]}},{"type":"Feature","properties":{"OBJECTID":"3446","Facility_N":"Kandege Dispensary","Type":"Dispensary","Owner":"Ministry of Health","County":"Kisumu","Sub_County":"Muhoroni","Division":"Muhoroni","Location":"Fort Ternan","Sub_Locati":"Fort Ternan","Constituen":"MUHORONI","Nearest_To":"Fort Ternan","Latitude":"-0.21452","Longitude":"35.3071"},"geometry":{"type":"Point","coordinates":[35.3071,-0.21452]}},{"type":"Feature","properties":{"OBJECTID":"3491","Facility_N":"Kanyagwal Dispensary","Type":"Dispensary","Owner":"Ministry of Health","County":"Kisumu","Sub_County":"Nyando","Division":"Kadibo","Location":"Bwanda","Sub_Locati":"Ogenya","Constituen":"NYANDO","Nearest_To":"Ahero","Latitude":"-0.23887","Longitude":"34.8797"},"geometry":{"type":"Point","coordinates":[34.8797,-0.23887]}},{"type":"Feature","properties":{"OBJECTID":"3802","Facility_N":"KASH DICE","Type":"Medical Clinic","Owner":"Non-Governmental Organizations","County":"Kisumu","Sub_County":"Kisumu East","Division":"Winam","Location":"kondele","Sub_Locati":"Manyatta B","Constituen":"KISUMU TOWN EAST","Nearest_To":"Kondele","Latitude":"-0.0981","Longitude":"34.77785"},"geometry":{"type":"Point","coordinates":[34.77785,-0.0981]}},{"type":"Feature","properties":{"OBJECTID":"3817","Facility_N":"Kasongo Dispensary","Type":"Dispensary","Owner":"Ministry of Health","County":"Kisumu","Sub_County":"Muhoroni","Division":"Miwani","Location":"Ombeyi","Sub_Locati":"Ramula","Constituen":"MUHORONI","Nearest_To":"Ombeyi","Latitude":"-0.16046","Longitude":"35.1999"},"geometry":{"type":"Point","coordinates":[35.1999,-0.16046]}},{"type":"Feature","properties":{"OBJECTID":"3880","Facility_N":"Katito Health Centre","Type":"Health Centre","Owner":"Ministry of Health","County":"Kisumu","Sub_County":"Nyakach","Division":"Lower Nyakach","Location":"North East Nyakach","Sub_Locati":"Agoro East","Constituen":"NYAKACH","Nearest_To":"Katito Market","Latitude":"-0.26973","Longitude":"34.97284"},"geometry":{"type":"Point","coordinates":[34.97284,-0.26973]}},{"type":"Feature","properties":{"OBJECTID":"3881","Facility_N":"Katolo-Manyatta Dispensary","Type":"Dispensary","Owner":"Ministry of Health","County":"Kisumu","Sub_County":"Nyando","Division":"Nyando","Location":"East Kano","Sub_Locati":"Achego","Constituen":"NYANDO","Nearest_To":"Ahero","Latitude":"-0.22764","Longitude":"34.96644"},"geometry":{"type":"Point","coordinates":[34.96644,-0.22764]}},{"type":"Feature","properties":{"OBJECTID":"3969","Facility_N":"Kemri Clinic","Type":"Health Centre","Owner":"Parastatal","County":"Kisumu","Sub_County":"Kisumu West","Division":"Winam","Location":"Central Kisumu","Sub_Locati":"Korando B","Constituen":"KISUMU TOWN EAST","Nearest_To":"Kisian Market","Latitude":"-0.0765","Longitude":"34.67583"},"geometry":{"type":"Point","coordinates":[34.67583,-0.0765]}},{"type":"Feature","properties":{"OBJECTID":"3982","Facility_N":"Kengen Clinic","Type":"Medical Clinic","Owner":"Parastatal","County":"Kisumu","Sub_County":"Nyakach","Division":"Upper Nyakach","Location":"Thurdibuoro","Sub_Locati":"West Koguta","Constituen":"NYAKACH","Nearest_To":"Kolwenyi","Latitude":"-0.33435","Longitude":"34.8521"},"geometry":{"type":"Point","coordinates":[34.8521,-0.33435]}},{"type":"Feature","properties":{"OBJECTID":"4208","Facility_N":"Kibigori Dispensary","Type":"Dispensary","Owner":"Ministry of Health","County":"Kisumu","Sub_County":"Muhoroni","Division":"Miwani","Location":"Chemelil","Sub_Locati":"Kibigori","Constituen":"MUHORONI","Nearest_To":"Masogo","Latitude":"-0.03911","Longitude":"35.18199"},"geometry":{"type":"Point","coordinates":[35.18199,-0.03911]}},{"type":"Feature","properties":{"OBJECTID":"4224","Facility_N":"Kibogo Dispensary","Type":"Dispensary","Owner":"Ministry of Health","County":"Kisumu","Sub_County":"Nyakach","Division":"Lower Nyakach","Location":"North E Nyakach","Sub_Locati":"Agoro West","Constituen":"NYAKACH","Nearest_To":"Kanyamurori","Latitude":"-0.29259","Longitude":"35.01362"},"geometry":{"type":"Point","coordinates":[35.01362,-0.29259]}},{"type":"Feature","properties":{"OBJECTID":"4232","Facility_N":"Kibos Medical Clinic","Type":"Medical Clinic","Owner":"Private Practice - Nurse / Midwife","County":"Kisumu","Sub_County":"Kisumu East","Division":"Winam","Location":"Wathorego","Sub_Locati":"Kajulu","Constituen":"KISUMU TOWN EAST","Nearest_To":"Kibos Market","Latitude":"-0.07127","Longitude":"34.81004"},"geometry":{"type":"Point","coordinates":[34.81004,-0.07127]}},{"type":"Feature","properties":{"OBJECTID":"4233","Facility_N":"Kibos Sugar Research Dispensary","Type":"Dispensary","Owner":"Ministry of Health","County":"Kisumu","Sub_County":"Kisumu East","Division":"Winam","Location":"Miwani","Sub_Locati":"Miwani West","Constituen":"KISUMU TOWN EAST","Nearest_To":"Kisumu","Latitude":"-0.03396","Longitude":"34.81761"},"geometry":{"type":"Point","coordinates":[34.81761,-0.03396]}},{"type":"Feature","properties":{"OBJECTID":"4348","Facility_N":"Kilimani Assessment Center","Type":"Medical Clinic","Owner":"Private Practice - Medical Specialist","County":"Kisumu","Sub_County":"Kisumu East","Division":"Winam","Location":"Township","Sub_Locati":"Township","Constituen":"KISUMU TOWN EAST","Nearest_To":"Jubilee Market","Latitude":"-0.10463","Longitude":"34.76014"},"geometry":{"type":"Point","coordinates":[34.76014,-0.10463]}},{"type":"Feature","properties":{"OBJECTID":"4436","Facility_N":"Kinasia Dispensary","Type":"Dispensary","Owner":"Ministry of Health","County":"Kisumu","Sub_County":"Nyando","Division":"Nyando","Location":"East Kano","Sub_Locati":"Katolo","Constituen":"NYANDO","Nearest_To":"Katito","Latitude":"-0.24871","Longitude":"35.02019"},"geometry":{"type":"Point","coordinates":[35.02019,-0.24871]}},{"type":"Feature","properties":{"OBJECTID":"4643","Facility_N":"Kisumu Beyond Zero Mobile Clinic","Type":"Dispensary","Owner":"Ministry of Health","County":"Kisumu","Sub_County":"Kisumu East","Division":"Winam","Location":"Township","Sub_Locati":"Market Milimani","Constituen":"KISUMU TOWN EAST","Nearest_To":"Central Business District","Latitude":"-0.10464","Longitude":"34.75321"},"geometry":{"type":"Point","coordinates":[34.75321,-0.10464]}},{"type":"Feature","properties":{"OBJECTID":"4644","Facility_N":"Kisumu Diagnostic Center","Type":"Laboratory (Stand-alone)","Owner":"Private Enterprise (Institution)","County":"Kisumu","Sub_County":"Kisumu East","Division":"Winam","Location":"Township","Sub_Locati":"Southern","Constituen":"KISUMU TOWN EAST","Nearest_To":"Central Business District","Latitude":"-0.10151","Longitude":"34.75298"},"geometry":{"type":"Point","coordinates":[34.75298,-0.10151]}},{"type":"Feature","properties":{"OBJECTID":"4645","Facility_N":"Kisumu District Hospital","Type":"District Hospital","Owner":"Ministry of Health","County":"Kisumu","Sub_County":"Kisumu East","Division":"Winam","Location":"Township","Sub_Locati":"Northern","Constituen":"KISUMU TOWN EAST","Nearest_To":"Kisumu","Latitude":"-0.10181","Longitude":"34.756"},"geometry":{"type":"Point","coordinates":[34.756,-0.10181]}},{"type":"Feature","properties":{"OBJECTID":"4646","Facility_N":"Kisumu International Airport Dispensary","Type":"Dispensary","Owner":"Ministry of Health","County":"Kisumu","Sub_County":"Kisumu West","Division":"Winam","Location":"Kisumu East","Sub_Locati":"Kogony","Constituen":"KISUMU TOWN EAST","Nearest_To":"Bandani","Latitude":"-0.08225","Longitude":"34.72832"},"geometry":{"type":"Point","coordinates":[34.72832,-0.08225]}},{"type":"Feature","properties":{"OBJECTID":"4647","Facility_N":"Kisumu Police Lines Dispensary","Type":"Dispensary","Owner":"Ministry of Health","County":"Kisumu","Sub_County":"Kisumu East","Division":"Winam","Location":"Manyatta B","Sub_Locati":" ","Constituen":"KISUMU TOWN EAST","Nearest_To":"Kisumu Bus Stage","Latitude":"-0.100856","Longitude":"34.760952"},"geometry":{"type":"Point","coordinates":[34.760952,-0.100856]}},{"type":"Feature","properties":{"OBJECTID":"4756","Facility_N":"K-Met Corkran","Type":"Dispensary","Owner":"Non-Governmental Organizations","County":"Kisumu","Sub_County":"Kisumu East","Division":"Winam","Location":"Nyawita","Sub_Locati":"Obunga","Constituen":"KISUMU TOWN WEST","Nearest_To":"Kisumu","Latitude":"-0.08296","Longitude":"34.76724"},"geometry":{"type":"Point","coordinates":[34.76724,-0.08296]}},{"type":"Feature","properties":{"OBJECTID":"4768","Facility_N":"Kodiaga Prison Health Centre","Type":"Health Centre","Owner":"Ministry of Health","County":"Kisumu","Sub_County":"Kisumu West","Division":"Winam","Location":"Central Kisumu","Sub_Locati":"Korando A","Constituen":"KISUMU TOWN EAST","Nearest_To":"Otonglo","Latitude":"-0.06211","Longitude":"34.70884"},"geometry":{"type":"Point","coordinates":[34.70884,-0.06211]}},{"type":"Feature","properties":{"OBJECTID":"4772","Facility_N":"Koduol Reru Dispensary","Type":"Dispensary","Owner":"Ministry of Health","County":"Kisumu","Sub_County":"Nyando","Division":"Kadibo","Location":"Bwanda","Sub_Locati":"Upper Bwanda","Constituen":"NYANDO","Nearest_To":"Rabuor Market","Latitude":"-0.1941","Longitude":"34.84215"},"geometry":{"type":"Point","coordinates":[34.84215,-0.1941]}},{"type":"Feature","properties":{"OBJECTID":"4807","Facility_N":"Kolenyo Dispensary","Type":"Dispensary","Owner":"Ministry of Health","County":"Kisumu","Sub_County":"Seme","Division":"Kombewa","Location":"South Central Seme","Sub_Locati":"East kanyadwera","Constituen":"KISUMU RURAL","Nearest_To":"Kolenyo Market","Latitude":"-0.09446","Longitude":"34.47192"},"geometry":{"type":"Point","coordinates":[34.47192,-0.09446]}},{"type":"Feature","properties":{"OBJECTID":"4821","Facility_N":"Kombewa District Hospital","Type":"District Hospital","Owner":"Ministry of Health","County":"Kisumu","Sub_County":"Seme","Division":"Kombewa","Location":"South Central Seme","Sub_Locati":"Upper Kombewa","Constituen":"KISUMU RURAL","Nearest_To":"Kombewa","Latitude":"-0.10345","Longitude":"34.51792"},"geometry":{"type":"Point","coordinates":[34.51792,-0.10345]}},{"type":"Feature","properties":{"OBJECTID":"4858","Facility_N":"Koru Dispensary","Type":"Dispensary","Owner":"Ministry of Health","County":"Kisumu","Sub_County":"Muhoroni","Division":"Muhoroni","Location":"Koru","Sub_Locati":"Koru","Constituen":"MUHORONI","Nearest_To":"Koru market","Latitude":"-0.1807","Longitude":"35.26685"},"geometry":{"type":"Point","coordinates":[35.26685,-0.1807]}},{"type":"Feature","properties":{"OBJECTID":"4859","Facility_N":"Koru Mission Health Centre","Type":"Health Centre","Owner":"Kenya Episcopal Conference-Catholic Secretariat","County":"Kisumu","Sub_County":"Muhoroni","Division":"Muhoroni","Location":"Koru","Sub_Locati":"Koru","Constituen":"MUHORONI","Nearest_To":"Koru","Latitude":"-0.18582","Longitude":"35.27415"},"geometry":{"type":"Point","coordinates":[35.27415,-0.18582]}},{"type":"Feature","properties":{"OBJECTID":"4860","Facility_N":"Korwenje Dispensary","Type":"Dispensary","Owner":"Ministry of Health","County":"Kisumu","Sub_County":"Seme","Division":"Kombewa","Location":"North Central Seme","Sub_Locati":"West Katieno","Constituen":"KISUMU RURAL","Nearest_To":"Korwenje Market","Latitude":"-0.04739","Longitude":"34.49191"},"geometry":{"type":"Point","coordinates":[34.49191,-0.04739]}},{"type":"Feature","properties":{"OBJECTID":"4868","Facility_N":"Kowino Dispensary","Type":"Dispensary","Owner":"Local Authority","County":"Kisumu","Sub_County":"Kisumu East","Division":"Winam","Location":"Kolwa West","Sub_Locati":"Nyalenda A","Constituen":"KISUMU TOWN EAST","Nearest_To":"Kisumu","Latitude":"-0.11414","Longitude":"34.76895"},"geometry":{"type":"Point","coordinates":[34.76895,-0.11414]}},{"type":"Feature","properties":{"OBJECTID":"4897","Facility_N":"Kuoyo Kaila Dispensary","Type":"Dispensary","Owner":"Ministry of Health","County":"Kisumu","Sub_County":"Seme","Division":"Maseno","Location":"East Seme","Sub_Locati":"Kaila","Constituen":"KISUMU RURAL","Nearest_To":"Paw Akuche Market","Latitude":"-0.08858","Longitude":"34.56683"},"geometry":{"type":"Point","coordinates":[34.56683,-0.08858]}},{"type":"Feature","properties":{"OBJECTID":"4905","Facility_N":"Kusa Health Centre","Type":"Health Centre","Owner":"Ministry of Health","County":"Kisumu","Sub_County":"Nyakach","Division":"Upper Nyakach","Location":"Thurdibuoro","Sub_Locati":"West Koguta","Constituen":"NYAKACH","Nearest_To":"Kolwenyi","Latitude":"-0.33545","Longitude":"34.85203"},"geometry":{"type":"Point","coordinates":[34.85203,-0.33545]}},{"type":"Feature","properties":{"OBJECTID":"5012","Facility_N":"Lake Basin Development Authority (Lbda) Dispensary","Type":"Dispensary","Owner":"Company Medical Service","County":"Kisumu","Sub_County":"Kisumu West","Division":"Winam","Location":"East Kisumu","Sub_Locati":"Kanyakwar","Constituen":"KISUMU TOWN EAST","Nearest_To":"Kisumu","Latitude":"-0.063484","Longitude":"34.7649"},"geometry":{"type":"Point","coordinates":[34.7649,-0.063484]}},{"type":"Feature","properties":{"OBJECTID":"5041","Facility_N":"Langi Kawino Dispensary","Type":"Dispensary","Owner":"Ministry of Health","County":"Kisumu","Sub_County":"Seme","Division":"Maseno","Location":"East Seme","Sub_Locati":"Kit Mikayi","Constituen":"KISUMU RURAL","Nearest_To":"Paw Akuche Market","Latitude":"-0.10116","Longitude":"34.57652"},"geometry":{"type":"Point","coordinates":[34.57652,-0.10116]}},{"type":"Feature","properties":{"OBJECTID":"5158","Facility_N":"Liverpool VCT (Kisumu East)","Type":"Medical Clinic","Owner":"Non-Governmental Organizations","County":"Kisumu","Sub_County":"Kisumu East","Division":"Winam","Location":"Township","Sub_Locati":"Northern","Constituen":"KISUMU TOWN EAST","Nearest_To":"Kisumu","Latitude":"-0.099621","Longitude":"34.7632"},"geometry":{"type":"Point","coordinates":[34.7632,-0.099621]}},{"type":"Feature","properties":{"OBJECTID":"5217","Facility_N":"Lolwe Dispensary","Type":"Dispensary","Owner":"Ministry of Health","County":"Kisumu","Sub_County":"Seme","Division":"Kombewa","Location":"South Central seme","Sub_Locati":"East Othany","Constituen":"KISUMU RURAL","Nearest_To":"Lolwe Market","Latitude":"-0.14716","Longitude":"34.53621"},"geometry":{"type":"Point","coordinates":[34.53621,-0.14716]}},{"type":"Feature","properties":{"OBJECTID":"5293","Facility_N":"Lumumba Health Centre","Type":"Health Centre","Owner":"Local Authority","County":"Kisumu","Sub_County":"Kisumu East","Division":"Winam","Location":"Township","Sub_Locati":"Kaloleni","Constituen":"KISUMU TOWN EAST","Nearest_To":"Kisumu","Latitude":"-0.09968","Longitude":"34.76599"},"geometry":{"type":"Point","coordinates":[34.76599,-0.09968]}},{"type":"Feature","properties":{"OBJECTID":"5313","Facility_N":"Lwala Kadawa Dispensary","Type":"Dispensary","Owner":"Ministry of Health","County":"Kisumu","Sub_County":"Kisumu West","Division":"Maseno","Location":"West Kisumu","Sub_Locati":"Upper Kadongo","Constituen":"KISUMU RURAL","Nearest_To":"Paw Akuche Market","Latitude":"-0.08013","Longitude":"34.62185"},"geometry":{"type":"Point","coordinates":[34.62185,-0.08013]}},{"type":"Feature","properties":{"OBJECTID":"5385","Facility_N":"Magina Health Center","Type":"Health Centre","Owner":"Ministry of Health","County":"Kisumu","Sub_County":"Nyando","Division":"Nyando","Location":"Wawidhi","Sub_Locati":"Magina","Constituen":"NYANDO","Nearest_To":"Ahero","Latitude":"-0.21349","Longitude":"34.93507"},"geometry":{"type":"Point","coordinates":[34.93507,-0.21349]}},{"type":"Feature","properties":{"OBJECTID":"5422","Facility_N":"Mainga Dispensary","Type":"Dispensary","Owner":"Ministry of Health","County":"Kisumu","Sub_County":"Kisumu West","Division":"Maseno","Location":"North West Kisumu","Sub_Locati":"South Kapuonja","Constituen":"KISUMU RURAL","Nearest_To":"Ulalo","Latitude":"-0.04727","Longitude":"34.6713"},"geometry":{"type":"Point","coordinates":[34.6713,-0.04727]}},{"type":"Feature","properties":{"OBJECTID":"5467","Facility_N":"Makindu Dispensary","Type":"Dispensary","Owner":"Ministry of Health","County":"Kisumu","Sub_County":"Muhoroni","Division":"Muhoroni","Location":"God Nyithindo","Sub_Locati":"Orego","Constituen":"MUHORONI","Nearest_To":"Muhoroni","Latitude":"-0.14086","Longitude":"35.12573"},"geometry":{"type":"Point","coordinates":[35.12573,-0.14086]}},{"type":"Feature","properties":{"OBJECTID":"5541","Facility_N":"Mama Plister Blair Health Centre","Type":"Health Centre","Owner":"Private Enterprise (Institution)","County":"Kisumu","Sub_County":"Muhoroni","Division":"Miwani","Location":"Ombeyi","Sub_Locati":"Ahero Irrigation scheme","Constituen":"MUHORONI","Nearest_To":"Ombeyi","Latitude":"-0.12894","Longitude":"34.96551"},"geometry":{"type":"Point","coordinates":[34.96551,-0.12894]}},{"type":"Feature","properties":{"OBJECTID":"5546","Facility_N":"Mamboleo Medical Clinic","Type":"Medical Clinic","Owner":"Private Practice - Nurse / Midwife","County":"Kisumu","Sub_County":"Kisumu East","Division":"Winam","Location":"Kajulu West","Sub_Locati":"Konya","Constituen":"KISUMU TOWN EAST","Nearest_To":"Mamboleo Shoping Centre","Latitude":"-0.05816","Longitude":"34.78539"},"geometry":{"type":"Point","coordinates":[34.78539,-0.05816]}},{"type":"Feature","properties":{"OBJECTID":"5588","Facility_N":"Manyatta Community Medical Clinic","Type":"Medical Clinic","Owner":"Private Practice - Clinical Officer","County":"Kisumu","Sub_County":"Kisumu East","Division":"Winam","Location":"Manyatta B","Sub_Locati":" ","Constituen":"KISUMU TOWN EAST","Nearest_To":"Kondele","Latitude":"-0.09366","Longitude":"34.78063"},"geometry":{"type":"Point","coordinates":[34.78063,-0.09366]}},{"type":"Feature","properties":{"OBJECTID":"5594","Facility_N":"Manyuanda Health Centre","Type":"Health Centre","Owner":"Ministry of Health","County":"Kisumu","Sub_County":"Seme","Division":"Kombewa","Location":"South West Seme","Sub_Locati":"East Kadinga","Constituen":"KISUMU RURAL","Nearest_To":"Manyuanda Market","Latitude":"-0.14141","Longitude":"34.46953"},"geometry":{"type":"Point","coordinates":[34.46953,-0.14141]}},{"type":"Feature","properties":{"OBJECTID":"5669","Facility_N":"Marie Stopes Nursing Home (Kisumu)","Type":"Nursing Home","Owner":"Non-Governmental Organizations","County":"Kisumu","Sub_County":"Kisumu East","Division":"Winam","Location":"Manyatta B","Sub_Locati":"Kondelle","Constituen":"KISUMU TOWN EAST","Nearest_To":"Kisumu","Latitude":"-0.0878","Longitude":"34.77025"},"geometry":{"type":"Point","coordinates":[34.77025,-0.0878]}},{"type":"Feature","properties":{"OBJECTID":"5735","Facility_N":"Masaba Hospital Kisumu","Type":"Other Hospital","Owner":"Private Practice - General Practitioner","County":"Kisumu","Sub_County":"Kisumu West","Division":"Maseno","Location":"West Kisumu","Sub_Locati":"West Karateng","Constituen":"KISUMU RURAL","Nearest_To":"Chulaimbo Market","Latitude":"-0.03925","Longitude":"34.62876"},"geometry":{"type":"Point","coordinates":[34.62876,-0.03925]}},{"type":"Feature","properties":{"OBJECTID":"5743","Facility_N":"Maseno Mission Hospital","Type":"Other Hospital","Owner":"Christian Health Association of Kenya","County":"Kisumu","Sub_County":"Kisumu West","Division":"Maseno","Location":"North West Kisumu","Sub_Locati":"West Karateng","Constituen":"KISUMU RURAL","Nearest_To":"Maseno Town","Latitude":"-0.00026","Longitude":"34.61169"},"geometry":{"type":"Point","coordinates":[34.61169,-0.00026]}},{"type":"Feature","properties":{"OBJECTID":"5744","Facility_N":"Maseno University AIDS Control Unit(City Campus)","Type":"VCT Centre (Stand-Alone)","Owner":"Academic (if registered)","County":"Kisumu","Sub_County":"Kisumu East","Division":"Winam","Location":"Central Kisumu","Sub_Locati":" ","Constituen":"KISUMU TOWN EAST","Nearest_To":"Milimani","Latitude":"-0.10749","Longitude":"34.75231"},"geometry":{"type":"Point","coordinates":[34.75231,-0.10749]}},{"type":"Feature","properties":{"OBJECTID":"5745","Facility_N":"Maseno University Medical Clinic","Type":"Dispensary","Owner":"Parastatal","County":"Kisumu","Sub_County":"Kisumu West","Division":"Maseno","Location":"North West Kisumu","Sub_Locati":"West Karateng","Constituen":"KISUMU RURAL","Nearest_To":"Maseno Town","Latitude":"-0.00152","Longitude":"34.6107"},"geometry":{"type":"Point","coordinates":[34.6107,-0.00152]}},{"type":"Feature","properties":{"OBJECTID":"5747","Facility_N":"Mashambani Dispensary","Type":"Dispensary","Owner":"Community","County":"Kisumu","Sub_County":"Muhoroni","Division":"Muhoroni","Location":"Chemeili","Sub_Locati":"Chemelil","Constituen":"MUHORONI","Nearest_To":"Chemelili Market","Latitude":"-0.08145","Longitude":"35.15148"},"geometry":{"type":"Point","coordinates":[35.15148,-0.08145]}},{"type":"Feature","properties":{"OBJECTID":"5761","Facility_N":"Masogo Sub District Hospital","Type":"Sub-District Hospital","Owner":"Ministry of Health","County":"Kisumu","Sub_County":"Muhoroni","Division":"Miwani","Location":"North East Kano","Sub_Locati":"Wang'aya 2","Constituen":"MUHORONI","Nearest_To":"Masogo","Latitude":"-0.09843","Longitude":"35.00522"},"geometry":{"type":"Point","coordinates":[35.00522,-0.09843]}},{"type":"Feature","properties":{"OBJECTID":"5895","Facility_N":"Mbaka Oromo Dispensary","Type":"Dispensary","Owner":"Ministry of Health","County":"Kisumu","Sub_County":"Kisumu West","Division":"Maseno","Location":"North West Kisumu","Sub_Locati":"East Karateng","Constituen":"KISUMU RURAL","Nearest_To":"Chulaimbo Market","Latitude":"-0.01469","Longitude":"34.63468"},"geometry":{"type":"Point","coordinates":[34.63468,-0.01469]}},{"type":"Feature","properties":{"OBJECTID":"5997","Facility_N":"Melkasons Clinic","Type":"Medical Clinic","Owner":"Private Practice - Nurse / Midwife","County":"Kisumu","Sub_County":"Seme","Division":"Kombewa","Location":"South Central Seme","Sub_Locati":"Upper Kombewa","Constituen":"KISUMU RURAL","Nearest_To":"Kombewa Market","Latitude":"-0.10864","Longitude":"34.52487"},"geometry":{"type":"Point","coordinates":[34.52487,-0.10864]}},{"type":"Feature","properties":{"OBJECTID":"6048","Facility_N":"Meridian Medical Centre-Kisumu","Type":"Medical Clinic","Owner":"Private Practice - General Practitioner","County":"Kisumu","Sub_County":"Kisumu East","Division":"Winam","Location":"Township","Sub_Locati":"Market Milimani","Constituen":"KISUMU TOWN EAST","Nearest_To":"Central Business District","Latitude":"-0.10465","Longitude":"34.75332"},"geometry":{"type":"Point","coordinates":[34.75332,-0.10465]}},{"type":"Feature","properties":{"OBJECTID":"6122","Facility_N":"Migosi Health Centre","Type":"Health Centre","Owner":"Local Authority","County":"Kisumu","Sub_County":"Kisumu East","Division":"Winam","Location":"Kondele","Sub_Locati":"Migosi","Constituen":"KISUMU TOWN EAST","Nearest_To":"Kisumu","Latitude":"-0.07607","Longitude":"34.78327"},"geometry":{"type":"Point","coordinates":[34.78327,-0.07607]}},{"type":"Feature","properties":{"OBJECTID":"6152","Facility_N":"Milenye Dispensary","Type":"Dispensary","Owner":"Ministry of Health","County":"Kisumu","Sub_County":"Muhoroni","Division":"Miwani","Location":"Nyangoma","Sub_Locati":"Kamswa South","Constituen":"MUHORONI","Nearest_To":"Awasi","Latitude":"-0.12134","Longitude":"35.06235"},"geometry":{"type":"Point","coordinates":[35.06235,-0.12134]}},{"type":"Feature","properties":{"OBJECTID":"6157","Facility_N":"Milimani Hospital","Type":"Other Hospital","Owner":"Private Enterprise (Institution)","County":"Kisumu","Sub_County":"Kisumu East","Division":"Winam","Location":"West Kolwa","Sub_Locati":"Nyalenda B","Constituen":"KISUMU TOWN EAST","Nearest_To":"Kisumu","Latitude":"-0.1217","Longitude":"34.75328"},"geometry":{"type":"Point","coordinates":[34.75328,-0.1217]}},{"type":"Feature","properties":{"OBJECTID":"6171","Facility_N":"Miranga Dispensary","Type":"Dispensary","Owner":"Ministry of Health","County":"Kisumu","Sub_County":"Muhoroni","Division":"Miwani","Location":"North East Kano","Sub_Locati":"Kabar East","Constituen":"MUHORONI","Nearest_To":"Masogo Market","Latitude":"0.09876","Longitude":"35.04103"},"geometry":{"type":"Point","coordinates":[35.04103,0.09876]}},{"type":"Feature","properties":{"OBJECTID":"6173","Facility_N":"Miranga Sub District Hospital","Type":"Sub-District Hospital","Owner":"Ministry of Health","County":"Kisumu","Sub_County":"Seme","Division":"Maseno","Location":"Otwenya","Sub_Locati":"East Kolunje","Constituen":"KISUMU RURAL","Nearest_To":"Paw Akuche Market","Latitude":"-0.07642","Longitude":"34.57942"},"geometry":{"type":"Point","coordinates":[34.57942,-0.07642]}},{"type":"Feature","properties":{"OBJECTID":"6220","Facility_N":"Miwani Dispensary","Type":"Dispensary","Owner":"Ministry of Health","County":"Kisumu","Sub_County":"Muhoroni","Division":"Miwani","Location":"Miwani","Sub_Locati":"Miwani North","Constituen":"MUHORONI","Nearest_To":"Miwani","Latitude":"-0.05023","Longitude":"34.97964"},"geometry":{"type":"Point","coordinates":[34.97964,-0.05023]}},{"type":"Feature","properties":{"OBJECTID":"6242","Facility_N":"Mnara Dispensary","Type":"Dispensary","Owner":"Ministry of Health","County":"Kisumu","Sub_County":"Muhoroni","Division":"Muhoroni","Location":"Muhoroni","Sub_Locati":"Owaga","Constituen":"MUHORONI","Nearest_To":"Muhoroni","Latitude":"-0.16969","Longitude":"35.23274"},"geometry":{"type":"Point","coordinates":[35.23274,-0.16969]}},{"type":"Feature","properties":{"OBJECTID":"6335","Facility_N":"Mosque Dispensary","Type":"Dispensary","Owner":"Ministry of Health","County":"Kisumu","Sub_County":"Kisumu East","Division":"Winam","Location":"Township","Sub_Locati":"Southern","Constituen":"KISUMU TOWN EAST","Nearest_To":"Kisumu","Latitude":"-0.08814","Longitude":"34.75798"},"geometry":{"type":"Point","coordinates":[34.75798,-0.08814]}},{"type":"Feature","properties":{"OBJECTID":"6417","Facility_N":"MTC Clinic (Kisumu)","Type":"Medical Clinic","Owner":"Private Enterprise (Institution)","County":"Kisumu","Sub_County":"Kisumu East","Division":"Winam","Location":"Kolwa West","Sub_Locati":"Manyatta B","Constituen":"KISUMU TOWN WEST","Nearest_To":"Kisumu","Latitude":"-0.089297","Longitude":"34.7845"},"geometry":{"type":"Point","coordinates":[34.7845,-0.089297]}},{"type":"Feature","properties":{"OBJECTID":"6474","Facility_N":"Muhoroni Sub-District Hospital","Type":"Sub-District Hospital","Owner":"Ministry of Health","County":"Kisumu","Sub_County":"Muhoroni","Division":"Muhoroni","Location":"Muhoroni","Sub_Locati":"Muhoroni Town","Constituen":"MUHORONI","Nearest_To":"Muhoroni","Latitude":"-0.15112","Longitude":"35.20573"},"geometry":{"type":"Point","coordinates":[35.20573,-0.15112]}},{"type":"Feature","properties":{"OBJECTID":"6475","Facility_N":"Muhoroni Sugar Company (Musco) Dispensary","Type":"Health Centre","Owner":"Company Medical Service","County":"Kisumu","Sub_County":"Muhoroni","Division":"Muhoroni","Location":"Muhoroni","Sub_Locati":"Muhoroni Town","Constituen":"MUHORONI","Nearest_To":"Muhoroni","Latitude":"-0.15182","Longitude":"35.18489"},"geometry":{"type":"Point","coordinates":[35.18489,-0.15182]}},{"type":"Feature","properties":{"OBJECTID":"6742","Facility_N":"Mv Patel Clinic","Type":"Medical Clinic","Owner":"Private Enterprise (Institution)","County":"Kisumu","Sub_County":"Kisumu East","Division":"Winam","Location":"Township","Sub_Locati":"Southern","Constituen":"KISUMU TOWN EAST","Nearest_To":"Kisumu","Latitude":"-0.10143","Longitude":"34.75305"},"geometry":{"type":"Point","coordinates":[34.75305,-0.10143]}},{"type":"Feature","properties":{"OBJECTID":"7088","Facility_N":"Nduru Kadero Dispensary","Type":"Dispensary","Owner":"Ministry of Health","County":"Kisumu","Sub_County":"Seme","Division":"Kombewa","Location":"North Central Seme","Sub_Locati":"Kadero_S","Constituen":"KISUMU RURAL","Nearest_To":"Kolenyo Market","Latitude":"-0.06836","Longitude":"34.46748"},"geometry":{"type":"Point","coordinates":[34.46748,-0.06836]}},{"type":"Feature","properties":{"OBJECTID":"7118","Facility_N":"Nehemiah International Dispensary","Type":"Dispensary","Owner":"Non-Governmental Organizations","County":"Kisumu","Sub_County":"Muhoroni","Division":"Winam","Location":"Miwani","Sub_Locati":"Miwani Central","Constituen":"MUHORONI","Nearest_To":"Karunga  Shoping Centre","Latitude":"-0.04807","Longitude":"34.90291"},"geometry":{"type":"Point","coordinates":[34.90291,-0.04807]}},{"type":"Feature","properties":{"OBJECTID":"7160","Facility_N":"New Spring Medical Care","Type":"Medical Clinic","Owner":"Private Practice - Clinical Officer","County":"Kisumu","Sub_County":"Kisumu East","Division":"Winam","Location":"Manyatta B","Sub_Locati":"Manyatta","Constituen":"KISUMU TOWN EAST","Nearest_To":"Kibuye Market-Kisumu Kakamega Road","Latitude":"-0.06392","Longitude":"34.786922"},"geometry":{"type":"Point","coordinates":[34.786922,-0.06392]}},{"type":"Feature","properties":{"OBJECTID":"7295","Facility_N":"Nightingale Medical Centre","Type":"Other Hospital","Owner":"Private Enterprise (Institution)","County":"Kisumu","Sub_County":"Kisumu East","Division":"Winam","Location":"Kondele","Sub_Locati":"Manyatta A","Constituen":"KISUMU TOWN EAST","Nearest_To":"Kisumu","Latitude":"-0.08317","Longitude":"34.7728"},"geometry":{"type":"Point","coordinates":[34.7728,-0.08317]}},{"type":"Feature","properties":{"OBJECTID":"7404","Facility_N":"Nyabola CDF Dispensary","Type":"Dispensary","Owner":"Ministry of Health","County":"Kisumu","Sub_County":"Nyakach","Division":"Lower Nyakach","Location":"Nyalunya","Sub_Locati":"Kabodho North","Constituen":"NYAKACH","Nearest_To":"Nyabola","Latitude":"-0.33879","Longitude":"34.90544"},"geometry":{"type":"Point","coordinates":[34.90544,-0.33879]}},{"type":"Feature","properties":{"OBJECTID":"7406","Facility_N":"Nyabondo Mission Hospital","Type":"Other Hospital","Owner":"Kenya Episcopal Conference-Catholic Secretariat","County":"Kisumu","Sub_County":"Nyakach","Division":"Upper Nyakach","Location":"Oboch","Sub_Locati":"Gari","Constituen":"NYAKACH","Nearest_To":"Nyabondo","Latitude":"-0.38168","Longitude":"34.97848"},"geometry":{"type":"Point","coordinates":[34.97848,-0.38168]}},{"type":"Feature","properties":{"OBJECTID":"7407","Facility_N":"Nyabondo Rehabilitation Centre","Type":"Dispensary","Owner":"Christian Health Association of Kenya","County":"Kisumu","Sub_County":"Nyakach","Division":"UPPER NYAKACH","Location":"SOUTH NYAKACH","Sub_Locati":"SOUTH NYAKACH","Constituen":"NYAKACH","Nearest_To":"NYABONDO MARKET","Latitude":"-0.38172","Longitude":"34.97882"},"geometry":{"type":"Point","coordinates":[34.97882,-0.38172]}},{"type":"Feature","properties":{"OBJECTID":"7432","Facility_N":"Nyahera Sub District Hospital","Type":"Sub-District Hospital","Owner":"Ministry of Health","County":"Kisumu","Sub_County":"Kisumu West","Division":"Winam","Location":"North Kisumu","Sub_Locati":"Nyahera","Constituen":"KISUMU TOWN EAST","Nearest_To":"Nyahera","Latitude":"-0.03495","Longitude":"34.71281"},"geometry":{"type":"Point","coordinates":[34.71281,-0.03495]}},{"type":"Feature","properties":{"OBJECTID":"7438","Facility_N":"Nyakach (AIC) Dispensary","Type":"Dispensary","Owner":"Christian Health Association of Kenya","County":"Kisumu","Sub_County":"Nyakach","Division":"Upper Nyakach","Location":"Oboch","Sub_Locati":"Gari","Constituen":"NYANDO","Nearest_To":"Oboch","Latitude":"-0.38434","Longitude":"34.93101"},"geometry":{"type":"Point","coordinates":[34.93101,-0.38434]}},{"type":"Feature","properties":{"OBJECTID":"7439","Facility_N":"Nyakach Sub County Hospital","Type":"District Hospital","Owner":"Ministry of Health","County":"Kisumu","Sub_County":"Nyakach","Division":"Lower Nyakach","Location":"Pap Onditi","Sub_Locati":"Kabodho East","Constituen":"NYAKACH","Nearest_To":"Pap Onditi","Latitude":"-0.31293","Longitude":"34.93741"},"geometry":{"type":"Point","coordinates":[34.93741,-0.31293]}},{"type":"Feature","properties":{"OBJECTID":"7444","Facility_N":"Nyakongo Dispensary","Type":"Dispensary","Owner":"Ministry of Health","County":"Kisumu","Sub_County":"Nyando","Division":"Nyando","Location":"Wawidhi","Sub_Locati":"Nyakongo","Constituen":"NYANDO","Nearest_To":"Awasi","Latitude":"-0.20083","Longitude":"35.01355"},"geometry":{"type":"Point","coordinates":[35.01355,-0.20083]}},{"type":"Feature","properties":{"OBJECTID":"7445","Facility_N":"Nyakunguru Dispensary","Type":"Dispensary","Owner":"Ministry of Health","County":"Kisumu","Sub_County":"Muhoroni","Division":"Miwani","Location":"Sidho east 1","Sub_Locati":" ","Constituen":"MUHORONI","Nearest_To":"Chemelili Market","Latitude":"0.09823","Longitude":"35.0732"},"geometry":{"type":"Point","coordinates":[35.0732,0.09823]}},{"type":"Feature","properties":{"OBJECTID":"7450","Facility_N":"Nyalenda Health Centre","Type":"Health Centre","Owner":"Local Authority","County":"Kisumu","Sub_County":"Kisumu East","Division":"Winam","Location":"West Kolwa","Sub_Locati":"Nyalenda B","Constituen":"KISUMU TOWN EAST","Nearest_To":"Kisumu","Latitude":"-0.1226","Longitude":"34.75211"},"geometry":{"type":"Point","coordinates":[34.75211,-0.1226]}},{"type":"Feature","properties":{"OBJECTID":"7459","Facility_N":"Nyalunya Dispensary","Type":"Dispensary","Owner":"Ministry of Health","County":"Kisumu","Sub_County":"Kisumu East","Division":"Winam","Location":"Kolwa Central","Sub_Locati":"Nyalunya","Constituen":"KISUMU TOWN EAST","Nearest_To":"Ragumo","Latitude":"-0.11746","Longitude":"34.80916"},"geometry":{"type":"Point","coordinates":[34.80916,-0.11746]}},{"type":"Feature","properties":{"OBJECTID":"7471","Facility_N":"Nyamarimba Dispensary","Type":"Dispensary","Owner":"Ministry of Health","County":"Kisumu","Sub_County":"Nyakach","Division":"Upper Nyakach","Location":"South West Nyakach","Sub_Locati":"West Kadianga","Constituen":"NYAKACH","Nearest_To":"Nyamarimba","Latitude":"-0.371554","Longitude":"34.90891"},"geometry":{"type":"Point","coordinates":[34.90891,-0.371554]}},{"type":"Feature","properties":{"OBJECTID":"7511","Facility_N":"Nyangande Health Centre","Type":"Health Centre","Owner":"Ministry of Health","County":"Kisumu","Sub_County":"Nyando","Division":"Kadibo","Location":"Kawino","Sub_Locati":"Kolal","Constituen":"NYANDO","Nearest_To":"Rabuor","Latitude":"-0.20814","Longitude":"34.84557"},"geometry":{"type":"Point","coordinates":[34.84557,-0.20814]}},{"type":"Feature","properties":{"OBJECTID":"7517","Facility_N":"Nyang'oma Health Centre","Type":"Health Centre","Owner":"Ministry of Health","County":"Kisumu","Sub_County":"Muhoroni","Division":"Miwani","Location":"Nyang'oma","Sub_Locati":"Wang'aya I","Constituen":"MUHORONI","Nearest_To":"Awasi","Latitude":"-0.14669","Longitude":"35.0441"},"geometry":{"type":"Point","coordinates":[35.0441,-0.14669]}},{"type":"Feature","properties":{"OBJECTID":"7519","Facility_N":"Nyangore Dispensary","Type":"Dispensary","Owner":"Ministry of Health","County":"Kisumu","Sub_County":"Muhoroni","Division":"Miwani","Location":"Chemelil","Sub_Locati":"nyangore","Constituen":"MUHORONI","Nearest_To":"potopoto market","Latitude":"0.03004","Longitude":"35.12339"},"geometry":{"type":"Point","coordinates":[35.12339,0.03004]}},{"type":"Feature","properties":{"OBJECTID":"7533","Facility_N":"Nyanza Provincial General Hospital (PGH)","Type":"Provincial General Hospital","Owner":"Ministry of Health","County":"Kisumu","Sub_County":"Kisumu East","Division":"Winam","Location":"Kolwa","Sub_Locati":"Manyatta B","Constituen":"KISUMU TOWN EAST","Nearest_To":"Kisumu","Latitude":"-0.08855","Longitude":"34.77038"},"geometry":{"type":"Point","coordinates":[34.77038,-0.08855]}},{"type":"Feature","properties":{"OBJECTID":"7556","Facility_N":"Nyaweri Deaf VCT","Type":"VCT Centre (Stand-Alone)","Owner":"Non-Governmental Organizations","County":"Kisumu","Sub_County":"Kisumu East","Division":"Winam","Location":"Manyatta B","Sub_Locati":" ","Constituen":"KISUMU TOWN EAST","Nearest_To":"Nearest NNPGH on Kisumu Kakamega Road","Latitude":"-0.09051","Longitude":"34.77177"},"geometry":{"type":"Point","coordinates":[34.77177,-0.09051]}},{"type":"Feature","properties":{"OBJECTID":"7634","Facility_N":"Ober Kamoth Health Centre","Type":"Health Centre","Owner":"Local Authority","County":"Kisumu","Sub_County":"Kisumu West","Division":"Winam","Location":"S.W Kisumu","Sub_Locati":"Kanyawegi","Constituen":"KISUMU TOWN EAST","Nearest_To":"Obambo","Latitude":"-0.11518","Longitude":"34.60952"},"geometry":{"type":"Point","coordinates":[34.60952,-0.11518]}},{"type":"Feature","properties":{"OBJECTID":"7636","Facility_N":"Oboch Dispensary","Type":"Dispensary","Owner":"Ministry of Health","County":"Kisumu","Sub_County":"Nyakach","Division":"Upper Nyakach","Location":"Oboch","Sub_Locati":"Gari","Constituen":"NYAKACH","Nearest_To":"Oboch","Latitude":"-0.38896","Longitude":"34.93802"},"geometry":{"type":"Point","coordinates":[34.93802,-0.38896]}},{"type":"Feature","properties":{"OBJECTID":"7637","Facility_N":"Obumba Dispensary","Type":"Dispensary","Owner":"Ministry of Health","County":"Kisumu","Sub_County":"Muhoroni","Division":"Miwani","Location":"Ombeyi","Sub_Locati":"Obumba","Constituen":"MUHORONI","Nearest_To":"Ombeyi","Latitude":"-0.09184","Longitude":"34.90175"},"geometry":{"type":"Point","coordinates":[34.90175,-0.09184]}},{"type":"Feature","properties":{"OBJECTID":"7660","Facility_N":"Ogen Dispensary","Type":"Dispensary","Owner":"Ministry of Health","County":"Kisumu","Sub_County":"Muhoroni","Division":"Muhoroni","Location":"Tamu","Sub_Locati":"East Soghor","Constituen":"MUHORONI","Nearest_To":"Soghor","Latitude":"-0.03917","Longitude":"35.18204"},"geometry":{"type":"Point","coordinates":[35.18204,-0.03917]}},{"type":"Feature","properties":{"OBJECTID":"7666","Facility_N":"Ogra Health Centre","Type":"Health Centre","Owner":"Non-Governmental Organizations","County":"Kisumu","Sub_County":"Muhoroni","Division":"Miwani","Location":"Ombeyi","Sub_Locati":"Ahero Irrigation Scheme","Constituen":"MUHORONI","Nearest_To":"Ombeyi","Latitude":"-0.11154","Longitude":"34.95048"},"geometry":{"type":"Point","coordinates":[34.95048,-0.11154]}},{"type":"Feature","properties":{"OBJECTID":"7672","Facility_N":"Ojola Dispensary","Type":"Dispensary","Owner":"Local Authority","County":"Kisumu","Sub_County":"Kisumu West","Division":"Winam","Location":"S.W Kisumu","Sub_Locati":"Ojola","Constituen":"KISUMU TOWN EAST","Nearest_To":"Kisian","Latitude":"-0.06627","Longitude":"34.64551"},"geometry":{"type":"Point","coordinates":[34.64551,-0.06627]}},{"type":"Feature","properties":{"OBJECTID":"7674","Facility_N":"Okana Dispensary","Type":"Dispensary","Owner":"Ministry of Health","County":"Kisumu","Sub_County":"Nyando","Division":"Kadibo","Location":"Kochieng East","Sub_Locati":"Okana","Constituen":"NYANDO","Nearest_To":"No Okana","Latitude":"-0.1393","Longitude":"34.89143"},"geometry":{"type":"Point","coordinates":[34.89143,-0.1393]}},{"type":"Feature","properties":{"OBJECTID":"7685","Facility_N":"Olasi Dispensary (Nyando)","Type":"Dispensary","Owner":"Ministry of Health","County":"Kisumu","Sub_County":"Nyando","Division":"Nyando","Location":"East Kano","Sub_Locati":"Achego","Constituen":"NYANDO","Nearest_To":"Katito","Latitude":"-0.26736","Longitude":"35.04453"},"geometry":{"type":"Point","coordinates":[35.04453,-0.26736]}},{"type":"Feature","properties":{"OBJECTID":"7767","Facility_N":"Olps Clinic","Type":"Dispensary","Owner":"Kenya Episcopal Conference-Catholic Secretariat","County":"Kisumu","Sub_County":"Kisumu East","Division":"Winam","Location":"Kolwa Central","Sub_Locati":"Kasule","Constituen":"KISUMU TOWN EAST","Nearest_To":"Kisumu","Latitude":"-0.07817","Longitude":"34.79355"},"geometry":{"type":"Point","coordinates":[34.79355,-0.07817]}},{"type":"Feature","properties":{"OBJECTID":"7807","Facility_N":"Onyinjo Dispensary","Type":"Dispensary","Owner":"Ministry of Health","County":"Kisumu","Sub_County":"Seme","Division":"Maseno","Location":"Otwenya","Sub_Locati":"South Ratta","Constituen":"KISUMU RURAL","Nearest_To":"Kondik Market","Latitude":"-0.07104","Longitude":"34.53725"},"geometry":{"type":"Point","coordinates":[34.53725,-0.07104]}},{"type":"Feature","properties":{"OBJECTID":"7808","Facility_N":"Onyuongo Dispensary","Type":"Dispensary","Owner":"Ministry of Health","County":"Kisumu","Sub_County":"Nyakach","Division":"Lower Nyakach","Location":"Jimo East","Sub_Locati":"Jimo East","Constituen":"NYAKACH","Nearest_To":"Sondu Market","Latitude":"-0.32515","Longitude":"35.00533"},"geometry":{"type":"Point","coordinates":[35.00533,-0.32515]}},{"type":"Feature","properties":{"OBJECTID":"7809","Facility_N":"Opapla Dispensary","Type":"Dispensary","Owner":"Ministry of Health","County":"Kisumu","Sub_County":"Seme","Division":"Kombewa","Location":"West Seme","Sub_Locati":"West Reru","Constituen":"KISUMU RURAL","Nearest_To":"Akala Market","Latitude":"-0.09656","Longitude":"34.41908"},"geometry":{"type":"Point","coordinates":[34.41908,-0.09656]}},{"type":"Feature","properties":{"OBJECTID":"7817","Facility_N":"Oren Health Centre","Type":"Health Centre","Owner":"Ministry of Health","County":"Kisumu","Sub_County":"Nyando","Division":"Nyando","Location":"Wawidhi","Sub_Locati":"Nyakongo","Constituen":"NYANDO","Nearest_To":" ","Latitude":"-0.18689","Longitude":"35.07167"},"geometry":{"type":"Point","coordinates":[35.07167,-0.18689]}},{"type":"Feature","properties":{"OBJECTID":"7820","Facility_N":"Oriang' Alwala Dispensary","Type":"Dispensary","Owner":"Ministry of Health","County":"Kisumu","Sub_County":"Seme","Division":"Kombewa","Location":"South West Seme","Sub_Locati":"Alwala","Constituen":"KISUMU RURAL","Nearest_To":"Alwala Market","Latitude":"-0.14491","Longitude":"34.48159"},"geometry":{"type":"Point","coordinates":[34.48159,-0.14491]}},{"type":"Feature","properties":{"OBJECTID":"7821","Facility_N":"Oriang Kanyadwera Dispensary","Type":"Dispensary","Owner":"Ministry of Health","County":"Kisumu","Sub_County":"Seme","Division":"Kombewa","Location":"South Central Seme","Sub_Locati":"West Kanyadwera","Constituen":"KISUMU RURAL","Nearest_To":"Near Riat Market, approximately 3 kms from Kisumu Bondo","Latitude":"-0.07289","Longitude":"34.45264"},"geometry":{"type":"Point","coordinates":[34.45264,-0.07289]}},{"type":"Feature","properties":{"OBJECTID":"7830","Facility_N":"Orongo Dispensary","Type":"Dispensary","Owner":"Ministry of Health","County":"Kisumu","Sub_County":"Kisumu East","Division":"Winam","Location":"West Kolwa","Sub_Locati":"Buoye","Constituen":"KISUMU TOWN EAST","Nearest_To":"Nyayo Market","Latitude":"-0.14321","Longitude":"34.78863"},"geometry":{"type":"Point","coordinates":[34.78863,-0.14321]}},{"type":"Feature","properties":{"OBJECTID":"7843","Facility_N":"Osewre Dispensary","Type":"Dispensary","Owner":"Ministry of Health","County":"Kisumu","Sub_County":"Seme","Division":"Kombewa","Location":"West Seme","Sub_Locati":"West Ngere","Constituen":"KISUMU RURAL","Nearest_To":"Reru Market","Latitude":"-0.13337","Longitude":"34.44436"},"geometry":{"type":"Point","coordinates":[34.44436,-0.13337]}},{"type":"Feature","properties":{"OBJECTID":"7863","Facility_N":"Otieno Owala Dispensary","Type":"Dispensary","Owner":"Ministry of Health","County":"Kisumu","Sub_County":"Seme","Division":"Kombewa","Location":"North Central Seme","Sub_Locati":"South Kowe","Constituen":"KISUMU RURAL","Nearest_To":"Kondik Market","Latitude":"-0.03547","Longitude":"34.52013"},"geometry":{"type":"Point","coordinates":[34.52013,-0.03547]}},{"type":"Feature","properties":{"OBJECTID":"7899","Facility_N":"Pand Pieri Community Health Centre","Type":"Dispensary","Owner":"Kenya Episcopal Conference-Catholic Secretariat","County":"Kisumu","Sub_County":"Kisumu East","Division":"Winam","Location":"West Kolwa","Sub_Locati":"Nyalenda B","Constituen":"KISUMU TOWN EAST","Nearest_To":"Kisumu","Latitude":"-0.11627","Longitude":"34.75698"},"geometry":{"type":"Point","coordinates":[34.75698,-0.11627]}},{"type":"Feature","properties":{"OBJECTID":"7951","Facility_N":"Pedo Dispensary","Type":"Dispensary","Owner":"Ministry of Health","County":"Kisumu","Sub_County":"Nyakach","Division":"Lower Nyakach","Location":"Kandaria West","Sub_Locati":"West Kandaria","Constituen":"NYAKACH","Nearest_To":"Osuoume","Latitude":"-0.33796","Longitude":"34.90802"},"geometry":{"type":"Point","coordinates":[34.90802,-0.33796]}},{"type":"Feature","properties":{"OBJECTID":"8033","Facility_N":"Port Florence Hospital","Type":"Other Hospital","Owner":"Private Enterprise (Institution)","County":"Kisumu","Sub_County":"Kisumu West","Division":"Winam","Location":"Township","Sub_Locati":"Bandani","Constituen":"KISUMU TOWN EAST","Nearest_To":"Kisumu","Latitude":"-0.07429","Longitude":"34.70296"},"geometry":{"type":"Point","coordinates":[34.70296,-0.07429]}},{"type":"Feature","properties":{"OBJECTID":"8121","Facility_N":"Rabuor Sub county Hospital","Type":"Sub-District Hospital","Owner":"Ministry of Health","County":"Kisumu","Sub_County":"Nyando","Division":"Kadibo","Location":"West Kochieng","Sub_Locati":"Kochieng","Constituen":"NYANDO","Nearest_To":"Rabuor","Latitude":"-0.15333","Longitude":"34.8299"},"geometry":{"type":"Point","coordinates":[34.8299,-0.15333]}},{"type":"Feature","properties":{"OBJECTID":"8124","Facility_N":"Rachar Sugar Belt Hospital","Type":"Health Centre","Owner":"Private Enterprise (Institution)","County":"Kisumu","Sub_County":"Muhoroni","Division":"Muhoroni","Location":"Muhoroni","Sub_Locati":"Muhoroni Town","Constituen":"MUHORONI","Nearest_To":"Muhoroni","Latitude":"-0.15497","Longitude":"35.19964"},"geometry":{"type":"Point","coordinates":[35.19964,-0.15497]}},{"type":"Feature","properties":{"OBJECTID":"8130","Facility_N":"Radienya Dispensary","Type":"Dispensary","Owner":"Ministry of Health","County":"Kisumu","Sub_County":"Nyakach","Division":"Upper Nyakach","Location":"East Kandiang'a","Sub_Locati":"Siany","Constituen":"NYAKACH","Nearest_To":"Sondu","Latitude":"-0.41036","Longitude":"34.97416"},"geometry":{"type":"Point","coordinates":[34.97416,-0.41036]}},{"type":"Feature","properties":{"OBJECTID":"8132","Facility_N":"Rae Dispensary","Type":"Dispensary","Owner":"Ministry of Health","County":"Kisumu","Sub_County":"Nyakach","Division":"Lower Nyakach","Location":"North Nyakach","Sub_Locati":"Gem Rae","Constituen":"NYAKACH","Nearest_To":"Katito","Latitude":"-0.2382","Longitude":"34.95691"},"geometry":{"type":"Point","coordinates":[34.95691,-0.2382]}},{"type":"Feature","properties":{"OBJECTID":"8147","Facility_N":"Railways Dispensary (Kisumu)","Type":"Dispensary","Owner":"Ministry of Health","County":"Kisumu","Sub_County":"Kisumu East","Division":"Winam","Location":"Township","Sub_Locati":"Northern","Constituen":"KISUMU TOWN EAST","Nearest_To":"Kisumu","Latitude":"-0.10109","Longitude":"34.74821"},"geometry":{"type":"Point","coordinates":[34.74821,-0.10109]}},{"type":"Feature","properties":{"OBJECTID":"8162","Facility_N":"Ramula Dispensary","Type":"Dispensary","Owner":"Ministry of Health","County":"Kisumu","Sub_County":"Muhoroni","Division":"Miwani","Location":"Ombeyi","Sub_Locati":"Ramula","Constituen":"MUHORONI","Nearest_To":"Ombeyi","Latitude":"-0.10579","Longitude":"34.95545"},"geometry":{"type":"Point","coordinates":[34.95545,-0.10579]}},{"type":"Feature","properties":{"OBJECTID":"8169","Facility_N":"Rang'ul Dispensary","Type":"Dispensary","Owner":"Ministry of Health","County":"Kisumu","Sub_County":"Nyakach","Division":"Lower Nyakach","Location":"Rang'ul","Sub_Locati":"Kasaye/ Wasare","Constituen":"NYAKACH","Nearest_To":"Katito Market","Latitude":"-0.28168","Longitude":"35.95438"},"geometry":{"type":"Point","coordinates":[35.95438,-0.28168]}},{"type":"Feature","properties":{"OBJECTID":"8187","Facility_N":"Ratta Health Centre","Type":"Health Centre","Owner":"Ministry of Health","County":"Kisumu","Sub_County":"Seme","Division":"Maseno","Location":"Otwenya","Sub_Locati":"North Rata","Constituen":"KISUMU RURAL","Nearest_To":"Ratta Market","Latitude":"-0.04529","Longitude":"34.53948"},"geometry":{"type":"Point","coordinates":[34.53948,-0.04529]}},{"type":"Feature","properties":{"OBJECTID":"8255","Facility_N":"Riat Dispensary","Type":"Dispensary","Owner":"Ministry of Health","County":"Kisumu","Sub_County":"Kisumu West","Division":"Maseno","Location":"West Kisumu","Sub_Locati":"North Kapuonja","Constituen":"KISUMU RURAL","Nearest_To":"Daranja Mbili Market","Latitude":"-0.02097","Longitude":"34.66381"},"geometry":{"type":"Point","coordinates":[34.66381,-0.02097]}},{"type":"Feature","properties":{"OBJECTID":"8294","Facility_N":"Rodi Dispensary","Type":"Dispensary","Owner":"Ministry of Health","County":"Kisumu","Sub_County":"Seme","Division":"Maseno","Location":"East Seme","Sub_Locati":"Kajulu Koker","Constituen":"KISUMU RURAL","Nearest_To":"Paw Akuche Market","Latitude":"-0.1188","Longitude":"34.57262"},"geometry":{"type":"Point","coordinates":[34.57262,-0.1188]}},{"type":"Feature","properties":{"OBJECTID":"8328","Facility_N":"Rota Dispensary","Type":"Dispensary","Owner":"Ministry of Health","County":"Kisumu","Sub_County":"Kisumu West","Division":"Winam","Location":"Sw Kisumu","Sub_Locati":"Ojola","Constituen":"KISUMU TOWN EAST","Nearest_To":"Kisian Market","Latitude":"-0.09282","Longitude":"34.6749"},"geometry":{"type":"Point","coordinates":[34.6749,-0.09282]}},{"type":"Feature","properties":{"OBJECTID":"8501","Facility_N":"Sango Rota Dispensary","Type":"Dispensary","Owner":"Ministry of Health","County":"Kisumu","Sub_County":"Nyakach","Division":"Upper Nyakach","Location":"West Nyakach","Sub_Locati":"Nyong'ong'a","Constituen":"NYAKACH","Nearest_To":"Sangorota","Latitude":"-0.34422","Longitude":"34.88895"},"geometry":{"type":"Point","coordinates":[34.88895,-0.34422]}},{"type":"Feature","properties":{"OBJECTID":"8542","Facility_N":"Sayyid Aysha Dispensary","Type":"Dispensary","Owner":"Non-Governmental Organizations","County":"Kisumu","Sub_County":"Kisumu East","Division":"Winam","Location":"Township","Sub_Locati":"Southern","Constituen":"KISUMU TOWN EAST","Nearest_To":"Kisumu","Latitude":"-0.10062","Longitude":"34.75038"},"geometry":{"type":"Point","coordinates":[34.75038,-0.10062]}},{"type":"Feature","properties":{"OBJECTID":"8615","Facility_N":"Shalom Medical Clinic","Type":"Medical Clinic","Owner":"Private Practice - Nurse / Midwife","County":"Kisumu","Sub_County":"Seme","Division":"Kombewa","Location":"West Seme","Sub_Locati":"East Reru","Constituen":"KISUMU RURAL","Nearest_To":"Reru Market Centre","Latitude":"-0.11168","Longitude":"34.45309"},"geometry":{"type":"Point","coordinates":[34.45309,-0.11168]}},{"type":"Feature","properties":{"OBJECTID":"8714","Facility_N":"Sigoti Health Centre","Type":"Health Centre","Owner":"Ministry of Health","County":"Kisumu","Sub_County":"Nyakach","Division":"Upper Nyakach","Location":"Sigoti","Sub_Locati":"Ramogi","Constituen":"NYAKACH","Nearest_To":"Sigoti","Latitude":"-0.34667","Longitude":"34.97091"},"geometry":{"type":"Point","coordinates":[34.97091,-0.34667]}},{"type":"Feature","properties":{"OBJECTID":"8742","Facility_N":"Simba Opepo Dispensary","Type":"Dispensary","Owner":"Local Authority","County":"Kisumu","Sub_County":"Kisumu East","Division":"Winam","Location":"West Kajulu","Sub_Locati":"Wath Orego","Constituen":"KISUMU TOWN EAST","Nearest_To":"Kisumu","Latitude":"-0.0475","Longitude":"34.79305"},"geometry":{"type":"Point","coordinates":[34.79305,-0.0475]}},{"type":"Feature","properties":{"OBJECTID":"8785","Facility_N":"Siriba Dispensary","Type":"Dispensary","Owner":"Ministry of Health","County":"Kisumu","Sub_County":"Kisumu West","Division":"Maseno","Location":"North West Kisumu","Sub_Locati":"West Karateng","Constituen":"KISUMU RURAL","Nearest_To":"Maseno Town","Latitude":"-0.00079","Longitude":"34.61057"},"geometry":{"type":"Point","coordinates":[34.61057,-0.00079]}},{"type":"Feature","properties":{"OBJECTID":"8851","Facility_N":"Sondu Health Centre","Type":"Health Centre","Owner":"Ministry of Health","County":"Kisumu","Sub_County":"Nyakach","Division":"Upper Nyakach","Location":"South Nyakach","Sub_Locati":"East Kadianga","Constituen":"NYAKACH","Nearest_To":"Sondu","Latitude":"-0.38696","Longitude":"35.0103"},"geometry":{"type":"Point","coordinates":[35.0103,-0.38696]}},{"type":"Feature","properties":{"OBJECTID":"8862","Facility_N":"SOS Children Medical Clinic","Type":"Medical Clinic","Owner":"Private Practice - Nurse / Midwife","County":"Kisumu","Sub_County":"Kisumu West","Division":"Otonglo","Location":"Kisumu Central","Sub_Locati":"Kogony","Constituen":"KISUMU RURAL","Nearest_To":"Kiboswa","Latitude":"-0.05882","Longitude":"34.73286"},"geometry":{"type":"Point","coordinates":[34.73286,-0.05882]}},{"type":"Feature","properties":{"OBJECTID":"8969","Facility_N":"St Clare Bolo Health Centre","Type":"Health Centre","Owner":"Kenya Episcopal Conference-Catholic Secretariat","County":"Kisumu","Sub_County":"Nyakach","Division":"Upper Nyakach","Location":"South West","Sub_Locati":"Upper Kadiang'A","Constituen":"NYAKACH","Nearest_To":"Kolwenyi","Latitude":"-0.34803","Longitude":"34.87407"},"geometry":{"type":"Point","coordinates":[34.87407,-0.34803]}},{"type":"Feature","properties":{"OBJECTID":"8972","Facility_N":"St Consolata Clinic","Type":"Medical Clinic","Owner":"Private Enterprise (Institution)","County":"Kisumu","Sub_County":"Kisumu East","Division":"Winam","Location":"Kajulu East","Sub_Locati":"Mamboleo","Constituen":"KISUMU TOWN EAST","Nearest_To":"Kisumu","Latitude":"-0.06069","Longitude":"34.77912"},"geometry":{"type":"Point","coordinates":[34.77912,-0.06069]}},{"type":"Feature","properties":{"OBJECTID":"8977","Facility_N":"St Elizabeth Chiga Health Centre","Type":"Health Centre","Owner":"Kenya Episcopal Conference-Catholic Secretariat","County":"Kisumu","Sub_County":"Kisumu East","Division":"Winam","Location":"East Kolwa","Sub_Locati":"Buoye","Constituen":"KISUMU TOWN EAST","Nearest_To":"Kisumu","Latitude":"-0.09891","Longitude":"34.84461"},"geometry":{"type":"Point","coordinates":[34.84461,-0.09891]}},{"type":"Feature","properties":{"OBJECTID":"9010","Facility_N":"St Jane Nursing Home","Type":"Nursing Home","Owner":"Other Faith Based","County":"Kisumu","Sub_County":"Nyakach","Division":"Upper Nyakach","Location":"Thurdibuoro","Sub_Locati":"West Koguta","Constituen":"NYAKACH","Nearest_To":" ","Latitude":"-0.33158","Longitude":"34.8456"},"geometry":{"type":"Point","coordinates":[34.8456,-0.33158]}},{"type":"Feature","properties":{"OBJECTID":"9032","Facility_N":"St Jones &Ring Road Health Clinic","Type":"Medical Clinic","Owner":"Private Enterprise (Institution)","County":"Kisumu","Sub_County":"Kisumu East","Division":"Winam","Location":"Kolwa West","Sub_Locati":"Nyalenda B","Constituen":"KISUMU TOWN EAST","Nearest_To":"Kisumu","Latitude":"-0.12409","Longitude":"34.75811"},"geometry":{"type":"Point","coordinates":[34.75811,-0.12409]}},{"type":"Feature","properties":{"OBJECTID":"9072","Facility_N":"St Jude's Clinic","Type":"Medical Clinic","Owner":"Private Enterprise (Institution)","County":"Kisumu","Sub_County":"Kisumu East","Division":"Winam","Location":"Township","Sub_Locati":"Southern","Constituen":"KISUMU TOWN EAST","Nearest_To":"Kisumu","Latitude":"-0.08062","Longitude":"34.7709"},"geometry":{"type":"Point","coordinates":[34.7709,-0.08062]}},{"type":"Feature","properties":{"OBJECTID":"9094","Facility_N":"St Luke's Hospital","Type":"Other Hospital","Owner":"Private Enterprise (Institution)","County":"Kisumu","Sub_County":"Kisumu East","Division":"Winam","Location":"Township","Sub_Locati":"Northern","Constituen":"KISUMU TOWN EAST","Nearest_To":"Kisumu","Latitude":"-0.10616","Longitude":"34.76167"},"geometry":{"type":"Point","coordinates":[34.76167,-0.10616]}},{"type":"Feature","properties":{"OBJECTID":"9108","Facility_N":"St Mark's Lela Dispensary","Type":"Dispensary","Owner":"Local Authority","County":"Kisumu","Sub_County":"Kisumu West","Division":"Winam","Location":"Central Kisumu","Sub_Locati":"Korando B","Constituen":"KISUMU TOWN EAST","Nearest_To":"Kisian","Latitude":"-0.07363","Longitude":"34.69519"},"geometry":{"type":"Point","coordinates":[34.69519,-0.07363]}},{"type":"Feature","properties":{"OBJECTID":"9168","Facility_N":"St Monica Hospital","Type":"Other Hospital","Owner":"Kenya Episcopal Conference-Catholic Secretariat","County":"Kisumu","Sub_County":"Kisumu East","Division":"Winam","Location":"East  Kajulu","Sub_Locati":"Konya","Constituen":"KISUMU TOWN EAST","Nearest_To":"Kisumu","Latitude":"-0.0422","Longitude":"34.76971"},"geometry":{"type":"Point","coordinates":[34.76971,-0.0422]}},{"type":"Feature","properties":{"OBJECTID":"9244","Facility_N":"St Vincent Clinic (Kisumu East)","Type":"Medical Clinic","Owner":"Private Enterprise (Institution)","County":"Kisumu","Sub_County":"Kisumu West","Division":"Winam","Location":"Township","Sub_Locati":"Southern","Constituen":"KISUMU TOWN EAST","Nearest_To":"Kisumu","Latitude":"-0.08018","Longitude":"34.76608"},"geometry":{"type":"Point","coordinates":[34.76608,-0.08018]}},{"type":"Feature","properties":{"OBJECTID":"9246","Facility_N":"St Vincents De Paul Health Centre","Type":"Health Centre","Owner":"Kenya Episcopal Conference-Catholic Secretariat","County":"Kisumu","Sub_County":"Muhoroni","Division":"Muhoroni","Location":"Muhoroni","Sub_Locati":"Muhoroni Town","Constituen":"MUHORONI","Nearest_To":"Muhoroni","Latitude":"-0.16969","Longitude":"35.23278"},"geometry":{"type":"Point","coordinates":[35.23278,-0.16969]}},{"type":"Feature","properties":{"OBJECTID":"9254","Facility_N":"St. Monica Hospital Town Clinic","Type":"Medical Clinic","Owner":"Kenya Episcopal Conference-Catholic Secretariat","County":"Kisumu","Sub_County":"Kisumu East","Division":"Winam","Location":"Kisumu Town","Sub_Locati":"Kaloleni","Constituen":"KISUMU TOWN EAST","Nearest_To":"Kibuye Market","Latitude":"-0.0919","Longitude":"34.76598"},"geometry":{"type":"Point","coordinates":[34.76598,-0.0919]}},{"type":"Feature","properties":{"OBJECTID":"9271","Facility_N":"Star Maternity & Nursing Home","Type":"Nursing Home","Owner":"Private Enterprise (Institution)","County":"Kisumu","Sub_County":"Kisumu East","Division":"Winam","Location":"Township","Sub_Locati":"Southern","Constituen":"KISUMU TOWN EAST","Nearest_To":"Kisumu","Latitude":"-0.12177","Longitude":"34.75308"},"geometry":{"type":"Point","coordinates":[34.75308,-0.12177]}},{"type":"Feature","properties":{"OBJECTID":"9289","Facility_N":"Stops Medical Clinic Kenya Ltd","Type":"Medical Clinic","Owner":"Private Practice - Nurse / Midwife","County":"Kisumu","Sub_County":"Kisumu East","Division":"Winam","Location":"Kondele","Sub_Locati":" ","Constituen":"KISUMU TOWN EAST","Nearest_To":"Kondele Market","Latitude":"-0.08295","Longitude":"34.77473"},"geometry":{"type":"Point","coordinates":[34.77473,-0.08295]}},{"type":"Feature","properties":{"OBJECTID":"9328","Facility_N":"Sunga Dispensary","Type":"Dispensary","Owner":"Ministry of Health","County":"Kisumu","Sub_County":"Kisumu West","Division":"Maseno","Location":"North West Kisumu","Sub_Locati":"Sunga","Constituen":"KISUMU RURAL","Nearest_To":"Lela Market","Latitude":"-0.0339","Longitude":"34.58966"},"geometry":{"type":"Point","coordinates":[34.58966,-0.0339]}},{"type":"Feature","properties":{"OBJECTID":"9416","Facility_N":"Tamu Health Centre","Type":"Health Centre","Owner":"Ministry of Health","County":"Kisumu","Sub_County":"Muhoroni","Division":"Muhoroni","Location":"Tamu","Sub_Locati":"God Abuoro","Constituen":"MUHORONI","Nearest_To":"Tamu","Latitude":"-0.10022","Longitude":"35.20432"},"geometry":{"type":"Point","coordinates":[35.20432,-0.10022]}},{"type":"Feature","properties":{"OBJECTID":"9508","Facility_N":"The Hope Medical Centre-Awasi","Type":"Nursing Home","Owner":"Christian Health Association of Kenya","County":"Kisumu","Sub_County":"Nyando","Division":"Nyando","Location":"Awasi","Sub_Locati":"Ayucha","Constituen":"NYANDO","Nearest_To":"Awasi","Latitude":"-0.16453","Longitude":"35.07167"},"geometry":{"type":"Point","coordinates":[35.07167,-0.16453]}},{"type":"Feature","properties":{"OBJECTID":"9689","Facility_N":"Tumaini DiCE Kisumu","Type":"Health Programme","Owner":"Non-Governmental Organizations","County":"Kisumu","Sub_County":"Kisumu East","Division":"Winam","Location":"Manyatta B","Sub_Locati":"Manyatta","Constituen":"KISUMU TOWN EAST","Nearest_To":"Nacelica Hotel","Latitude":"-0.1031","Longitude":"34.76178"},"geometry":{"type":"Point","coordinates":[34.76178,-0.1031]}},{"type":"Feature","properties":{"OBJECTID":"9724","Facility_N":"Tumaini Sondu Disc","Type":"Medical Clinic","Owner":"Private Practice - Clinical Officer","County":"Kisumu","Sub_County":"Nyakach","Division":"Upper Nyakach","Location":"South East Nyakach","Sub_Locati":"East Kadianga","Constituen":"NYAKACH","Nearest_To":"Sondu Market","Latitude":"-0.38958","Longitude":"35.01158"},"geometry":{"type":"Point","coordinates":[35.01158,-0.38958]}},{"type":"Feature","properties":{"OBJECTID":"9759","Facility_N":"Tuungane Youth Centre (Kisumu East)","Type":"Medical Clinic","Owner":"Non-Governmental Organizations","County":"Kisumu","Sub_County":"Kisumu East","Division":"Winam","Location":"Township","Sub_Locati":"Southern","Constituen":"KISUMU TOWN EAST","Nearest_To":"Kisumu","Latitude":"-0.089975","Longitude":"34.76612"},"geometry":{"type":"Point","coordinates":[34.76612,-0.089975]}},{"type":"Feature","properties":{"OBJECTID":"9761","Facility_N":"Tuungane Youth Transition Centre","Type":"Dispensary","Owner":"Non-Governmental Organizations","County":"Kisumu","Sub_County":"Kisumu East","Division":"Winam","Location":"Manyatta B","Sub_Locati":"Kondelle","Constituen":"KISUMU TOWN EAST","Nearest_To":"Kibuye Market","Latitude":"-0.08976","Longitude":"34.76629"},"geometry":{"type":"Point","coordinates":[34.76629,-0.08976]}},{"type":"Feature","properties":{"OBJECTID":"9799","Facility_N":"Umbrella Health Clinic","Type":"Medical Clinic","Owner":"Private Enterprise (Institution)","County":"Kisumu","Sub_County":"Nyando","Division":"Kadibo","Location":"West Kochieng","Sub_Locati":"Nyamware","Constituen":"NYANDO","Nearest_To":" ","Latitude":"-0.15065","Longitude":"34.82161"},"geometry":{"type":"Point","coordinates":[34.82161,-0.15065]}},{"type":"Feature","properties":{"OBJECTID":"9872","Facility_N":"Usoma Dispensary","Type":"Dispensary","Owner":"Local Authority","County":"Kisumu","Sub_County":"Kisumu West","Division":"Winam","Location":"Central Kisumu","Sub_Locati":"Bandani","Constituen":"KISUMU TOWN EAST","Nearest_To":"Otonglo","Latitude":"-0.10381","Longitude":"34.71978"},"geometry":{"type":"Point","coordinates":[34.71978,-0.10381]}},{"type":"Feature","properties":{"OBJECTID":"9921","Facility_N":"Victoria Sub District Hospital","Type":"Sub-District Hospital","Owner":"Ministry of Health","County":"Kisumu","Sub_County":"Kisumu East","Division":"Winam","Location":"Township","Sub_Locati":"Northern","Constituen":"KISUMU TOWN EAST","Nearest_To":"Behind the Nyanza Provincial Head quarters","Latitude":"-0.11147","Longitude":"34.75107"},"geometry":{"type":"Point","coordinates":[34.75107,-0.11147]}}]}